Workbook
Name ERP: [1]FCFF!$F$21
Name ERP: #REF!
Name ERP: FCFF!$F$22
Name RF: [1]FCFF!$F$20
Name RF: #REF!
Name RF: FCFF!$F$21
Name rf_rate: #REF!
Name rf_rate: FCFF!$F$21
Name tap_rate: [1]FCFF!$F$18
Name tap_rate: #REF!
Name tap_rate: FCFF!$F$19
Name Taper_rate: #REF!
Name Taper_rate: FCFF!$C$21
Name tax_rate: [1]FCFF!$F$22
Name tax_rate: #REF!
Name tax_rate: FCFF!$F$23
Name UPDATE: '[1]Data sheet'!$E$1
Name UPDATE: '[2]Data Sheet'!$E$1
Name UPDATE: 'Data Sheet'!$E$1

Sheet Profit & Loss
A1: ='Data Sheet'!B1 -> JSW STEEL LTD | H1: =UPDATE -> JSW STEEL LTD | M1: SCREENER.IN
A3: Narration | B3: ='Data Sheet'!B16 -> 42825 | C3: ='Data Sheet'!C16 -> 43190 | D3: ='Data Sheet'!D16 -> 43555 | E3: ='Data Sheet'!E16 -> 43921 | F3: ='Data Sheet'!F16 -> 44286 | G3: ='Data Sheet'!G16 -> 44651 | H3: ='Data Sheet'!H16 -> 45016 | I3: ='Data Sheet'!I16 -> 45382 | ... K3: ='Data Sheet'!K16 -> 46112 | L3: Trailing | M3: Best Case | N3: Worst Case
A4: Sales | B4: ='Data Sheet'!B17 -> 55604 | C4: ='Data Sheet'!C17 -> 71933 | D4: ='Data Sheet'!D17 -> 84757 | E4: ='Data Sheet'!E17 -> 73326 | F4: ='Data Sheet'!F17 -> 79839 | G4: ='Data Sheet'!G17 -> 146371 | H4: ='Data Sheet'!H17 -> 165960 | I4: ='Data Sheet'!I17 -> 175006 | ... K4: ='Data Sheet'!K17 -> 185470 | L4: =SUM(Quarters!H4:K4) -> 185470 | M4: =$K4+M23*K4 -> 203757.29 | N4: =$K4+N23*L4 -> 192470.31
A5: Expenses | B5: =SUM('Data Sheet'!B18,'Data Sheet'!B20:B24, -1*'Data Sheet'!B19) -> 43296 | C5: =SUM('Data Sheet'!C18,'Data Sheet'!C20:C24, -1*'Data Sheet'!C19) -> 57017 | D5: =SUM('Data Sheet'!D18,'Data Sheet'!D20:D24, -1*'Data Sheet'!D19) -> 65827 | E5: =SUM('Data Sheet'!E18,'Data Sheet'!E20:E24, -1*'Data Sheet'!E19) -> 61513 | F5: =SUM('Data Sheet'!F18,'Data Sheet'!F20:F24, -1*'Data Sheet'!F19) -> 59661 | G5: =SUM('Data Sheet'!G18,'Data Sheet'!G20:G24, -1*'Data Sheet'!G19) -> 107257 | H5: =SUM('Data Sheet'!H18,'Data Sheet'!H20:H24, -1*'Data Sheet'!H19) -> 147490 | I5: =SUM('Data Sheet'!I18,'Data Sheet'!I20:I24, -1*'Data Sheet'!I19) -> 146849 | ... K5: =SUM('Data Sheet'!K18,'Data Sheet'!K20:K24, -1*'Data Sheet'!K19) -> 156124 | L5: =SUM(Quarters!H5:K5) -> 156124 | M5: =M4-M6 -> 171517.78 | N5: =N4-N6 -> 163296.86
A6: Operating Profit | B6: =B4-B5 -> 12308 | C6: =C4-C5 -> 14916 | D6: =D4-D5 -> 18930 | E6: =E4-E5 -> 11813 | F6: =F4-F5 -> 20178 | G6: =G4-G5 -> 39114 | H6: =H4-H5 -> 18470 | I6: =I4-I5 -> 28157 | ... K6: =K4-K5 -> 29346 | L6: =SUM(Quarters!H6:K6) -> 29346 | M6: =M4*M24 -> 32239.508 | N6: =N4*N24 -> 29173.452
A7: Other Income | B7: ='Data Sheet'!B25 -> 18 | C7: ='Data Sheet'!C25 -> -177 | D7: ='Data Sheet'!D25 -> 196 | E7: ='Data Sheet'!E25 -> -289 | F7: ='Data Sheet'!F25 -> 473 | G7: ='Data Sheet'!G25 -> 1600 | H7: ='Data Sheet'!H25 -> 1561 | I7: ='Data Sheet'!I25 -> 1500 | ... K7: ='Data Sheet'!K25 -> 18607 | L7: =SUM(Quarters!H7:K7) -> 18607 | M7: 0 | N7: 0
A8: Depreciation | B8: ='Data Sheet'!B26 -> 3430 | C8: ='Data Sheet'!C26 -> 3387 | D8: ='Data Sheet'!D26 -> 4041 | E8: ='Data Sheet'!E26 -> 4246 | F8: ='Data Sheet'!F26 -> 4679 | G8: ='Data Sheet'!G26 -> 6001 | H8: ='Data Sheet'!H26 -> 7474 | I8: ='Data Sheet'!I26 -> 8172 | ... K8: ='Data Sheet'!K26 -> 9601 | L8: =SUM(Quarters!H8:K8) -> 9601 | M8: =+$L8 -> 9601 | N8: =+$L8 -> 9601
A9: Interest | B9: ='Data Sheet'!B27 -> 3768 | C9: ='Data Sheet'!C27 -> 3701 | D9: ='Data Sheet'!D27 -> 3917 | E9: ='Data Sheet'!E27 -> 4265 | F9: ='Data Sheet'!F27 -> 3957 | G9: ='Data Sheet'!G27 -> 4968 | H9: ='Data Sheet'!H27 -> 6902 | I9: ='Data Sheet'!I27 -> 8105 | ... K9: ='Data Sheet'!K27 -> 9102 | L9: =SUM(Quarters!H9:K9) -> 9102 | M9: =+$L9 -> 9102 | N9: =+$L9 -> 9102
A10: Profit before tax | B10: ='Data Sheet'!B28 -> 5128 | C10: ='Data Sheet'!C28 -> 7651 | D10: ='Data Sheet'!D28 -> 11168 | E10: ='Data Sheet'!E28 -> 3013 | F10: ='Data Sheet'!F28 -> 12015 | G10: ='Data Sheet'!G28 -> 29745 | H10: ='Data Sheet'!H28 -> 5655 | I10: ='Data Sheet'!I28 -> 13380 | ... K10: ='Data Sheet'!K28 -> 29250 | L10: =SUM(Quarters!H10:K10) -> 29250 | M10: =M6+M7-SUM(M8:M9) -> 13536.508 | N10: =N6+N7-SUM(N8:N9) -> 10470.452
A11: Tax | B11: ='Data Sheet'!B29 -> 1674 | C11: ='Data Sheet'!C29 -> 1538 | D11: ='Data Sheet'!D29 -> 3644 | E11: ='Data Sheet'!E29 -> -906 | F11: ='Data Sheet'!F29 -> 4142 | G11: ='Data Sheet'!G29 -> 8807 | H11: ='Data Sheet'!H29 -> 1516 | I11: ='Data Sheet'!I29 -> 4407 | ... K11: ='Data Sheet'!K29 -> 3742 | L11: =SUM(Quarters!H11:K11) -> 3742 | M11: =IF($L10>0,$L11/$L10,0) -> 0.12793162 | N11: =IF($L10>0,$L11/$L10,0) -> 0.12793162
A12: Net profit | B12: ='Data Sheet'!B30 -> 3523 | C12: ='Data Sheet'!C30 -> 6214 | D12: ='Data Sheet'!D30 -> 7639 | E12: ='Data Sheet'!E30 -> 4030 | F12: ='Data Sheet'!F30 -> 7911 | G12: ='Data Sheet'!G30 -> 20665 | H12: ='Data Sheet'!H30 -> 4144 | I12: ='Data Sheet'!I30 -> 8812 | ... K12: ='Data Sheet'!K30 -> 22316 | L12: =SUM(Quarters!H12:K12) -> 22316 | M12: =M10-M11*M10 -> 11804.76 | N12: =N10-N11*N10 -> 9130.9504
A13: EPS | B13: =IF('Data Sheet'!B93>0,B12/'Data Sheet'!B93,0) -> 14.574715 | C13: =IF('Data Sheet'!C93>0,C12/'Data Sheet'!C93,0) -> 25.70743 | D13: =IF('Data Sheet'!D93>0,D12/'Data Sheet'!D93,0) -> 31.602681 | E13: =IF('Data Sheet'!E93>0,E12/'Data Sheet'!E93,0) -> 16.672183 | F13: =IF('Data Sheet'!F93>0,F12/'Data Sheet'!F93,0) -> 32.72795 | G13: =IF('Data Sheet'!G93>0,G12/'Data Sheet'!G93,0) -> 85.491478 | H13: =IF('Data Sheet'!H93>0,H12/'Data Sheet'!H93,0) -> 17.143803 | I13: =IF('Data Sheet'!I93>0,I12/'Data Sheet'!I93,0) -> 36.033531 | ... K13: =IF('Data Sheet'!K93>0,K12/'Data Sheet'!K93,0) -> 91.253322 | L13: =IF('Data Sheet'!$B6>0,'Profit & Loss'!L12/'Data Sheet'!$B6,0) -> 91.255039 | M13: =IF('Data Sheet'!$B6>0,'Profit & Loss'!M12/'Data Sheet'!$B6,0) -> 48.272264 | N13: =IF('Data Sheet'!$B6>0,'Profit & Loss'!N12/'Data Sheet'!$B6,0) -> 37.338467
A14: Price to earning | B14: =IF(B15>0,B15/B13,"") -> 12.912774 | C14: =IF(C15>0,C15/C13,"") -> 11.208822 | D14: =IF(D15>0,D15/D13,"") -> 9.2729475 | E14: =IF(E15>0,E15/E13,"") -> 8.7720968 | F14: =IF(F15>0,F15/F13,"") -> 14.313454 | G14: =IF(G15>0,G15/G13,"") -> 8.5698601 | H14: =IF(H15>0,H15/H13,"") -> 40.136953 | I14: =IF(I15>0,I15/I13,"") -> 23.039652 | ... K14: =IF(K15>0,K15/K13,"") -> 12.300922 | L14: =IF(L13>0,L15/L13,0) -> 14.004706 | M14: =M25 -> 30.886945 | N14: =N25 -> 14.004706
A15: Price | B15: ='Data Sheet'!B90 -> 188.2 | C15: ='Data Sheet'!C90 -> 288.15 | D15: ='Data Sheet'!D90 -> 293.05 | E15: ='Data Sheet'!E90 -> 146.25 | F15: ='Data Sheet'!F90 -> 468.45 | G15: ='Data Sheet'!G90 -> 732.65 | H15: ='Data Sheet'!H90 -> 688.1 | I15: ='Data Sheet'!I90 -> 830.2 | ... K15: ='Data Sheet'!K90 -> 1122.5 | L15: ='Data Sheet'!B8 -> 1278 | M15: =M13*M14 -> 1490.9828 | N15: =N13*N14 -> 522.91426
A17: RATIOS:
A18: Dividend Payout | B18: =IF('Data Sheet'!B30>0, 'Data Sheet'!B31/'Data Sheet'!B30, 0) -> 0.19223673 | C18: =IF('Data Sheet'!C30>0, 'Data Sheet'!C31/'Data Sheet'!C30, 0) -> 0.15551979 | D18: =IF('Data Sheet'!D30>0, 'Data Sheet'!D31/'Data Sheet'!D30, 0) -> 0.16155256 | E18: =IF('Data Sheet'!E30>0, 'Data Sheet'!E31/'Data Sheet'!E30, 0) -> 0.14937965 | F18: =IF('Data Sheet'!F30>0, 'Data Sheet'!F31/'Data Sheet'!F30, 0) -> 0.24813551 | G18: =IF('Data Sheet'!G30>0, 'Data Sheet'!G31/'Data Sheet'!G30, 0) -> 0.25271474 | H18: =IF('Data Sheet'!H30>0, 'Data Sheet'!H31/'Data Sheet'!H30, 0) -> 0.24695946 | I18: =IF('Data Sheet'!I30>0, 'Data Sheet'!I31/'Data Sheet'!I30, 0) -> 0.25266682 | ... K18: =IF('Data Sheet'!K30>0, 'Data Sheet'!K31/'Data Sheet'!K30, 0) -> 0.097038
A19: OPM | B19: =IF(B6>0,B6/B4,0) -> 0.22135098 | C19: =IF(C6>0,C6/C4,0) -> 0.20735963 | D19: =IF(D6>0,D6/D4,0) -> 0.22334438 | E19: =IF(E6>0,E6/E4,0) -> 0.16110247 | F19: =IF(F6>0,F6/F4,0) -> 0.25273363 | G19: =IF(G6>0,G6/G4,0) -> 0.26722507 | H19: =IF(H6>0,H6/H4,0) -> 0.11129188 | I19: =IF(I6>0,I6/I4,0) -> 0.16089163 | ... L19: =IF(L6>0,L6/L4,0) -> 0.15822505
G22: TRENDS: | H22: 10 YEARS | I22: 7 YEARS | J22: 5 YEARS | K22: 3 YEARS | L22: RECENT | M22: BEST | N22: WORST
G23: Sales Growth | H23: =IF(B4=0,"",POWER($K4/B4,1/9)-1) -> 0.1432198 | I23: =IF(D4=0,"",POWER($K4/D4,1/7)-1) -> 0.11836983 | J23: =IF(F4=0,"",POWER($K4/F4,1/5)-1) -> 0.18361842 | K23: =IF(H4=0,"",POWER($K4/H4, 1/3)-1) -> 0.037743644 | L23: =IF(ISERROR(MAX(IF(J4=0,"",(K4-J4)/J4),IF(K4=0,"",(L4-K4)/K4))),"",MAX(IF(J4=0,"",(K4-J4)/J4),IF(K4=0,"",(L4-K4)/K4))) -> 0.098599725 | M23: =MAX(K23:L23) -> 0.098599725 | N23: =MIN(H23:L23) -> 0.037743644
G24: OPM | H24: =IF(SUM(B4:$K$4)=0,"",SUMPRODUCT(B19:$K$19,B4:$K$4)/SUM(B4:$K$4)) -> 0.17890712 | I24: =IF(SUM(E4:$K$4)=0,"",SUMPRODUCT(E19:$K$19,E4:$K$4)/SUM(E4:$K$4)) -> 0.17069128 | J24: =IF(SUM(G4:$K$4)=0,"",SUMPRODUCT(G19:$K$19,G4:$K$4)/SUM(G4:$K$4)) -> 0.16374397 | K24: =IF(SUM(I4:$K$4)=0, "", SUMPRODUCT(I19:$K$19,I4:$K$4)/SUM(I4:$K$4)) -> 0.15157378 | L24: =L19 -> 0.15822505 | M24: =MAX(K24:L24) -> 0.15822505 | N24: =MIN(H24:L24) -> 0.15157378
G25: Price to Earning | H25: =IF(ISERROR(AVERAGEIF(B14:$L14,">0")),"",AVERAGEIF(B14:$L14,">0")) -> 20.794062 | I25: =IF(ISERROR(AVERAGEIF(E14:$L14,">0")),"",AVERAGEIF(E14:$L14,">0")) -> 24.417518 | J25: =IF(ISERROR(AVERAGEIF(G14:$L14,">0")),"",AVERAGEIF(G14:$L14,">0")) -> 28.709099 | K25: =IF(ISERROR(AVERAGEIF(I14:$L14,">0")),"",AVERAGEIF(I14:$L14,">0")) -> 30.886945 | L25: =L14 -> 14.004706 | M25: =MAX(K25:L25) -> 30.886945 | N25: =MIN(H25:L25) -> 14.004706

Sheet Quarters
A1: ='Profit & Loss'!A1 -> JSW STEEL LTD | E1: =UPDATE -> JSW STEEL LTD | J1: SCREENER.IN
A3: Narration | B3: ='Data Sheet'!B41 -> 45291 | C3: ='Data Sheet'!C41 -> 45382 | D3: ='Data Sheet'!D41 -> 45473 | E3: ='Data Sheet'!E41 -> 45565 | F3: ='Data Sheet'!F41 -> 45657 | G3: ='Data Sheet'!G41 -> 45747 | H3: ='Data Sheet'!H41 -> 45838 | I3: ='Data Sheet'!I41 -> 45930 | ... K3: ='Data Sheet'!K41 -> 46112
A4: Sales | B4: ='Data Sheet'!B42 -> 41940 | C4: ='Data Sheet'!C42 -> 46269 | D4: ='Data Sheet'!D42 -> 42943 | E4: ='Data Sheet'!E42 -> 39684 | F4: ='Data Sheet'!F42 -> 41378 | G4: ='Data Sheet'!G42 -> 44819 | H4: ='Data Sheet'!H42 -> 43147 | I4: ='Data Sheet'!I42 -> 45152 | ... K4: ='Data Sheet'!K42 -> 51180
A5: Expenses | B5: ='Data Sheet'!B43 -> 34776 | C5: ='Data Sheet'!C43 -> 40243 | D5: ='Data Sheet'!D43 -> 37445 | E5: ='Data Sheet'!E43 -> 34309 | F5: ='Data Sheet'!F43 -> 35799 | G5: ='Data Sheet'!G43 -> 38684 | H5: ='Data Sheet'!H43 -> 35671 | I5: ='Data Sheet'!I43 -> 38125 | ... K5: ='Data Sheet'!K43 -> 42716
A6: Operating Profit | B6: ='Data Sheet'!B50 -> 7164 | C6: ='Data Sheet'!C50 -> 6026 | D6: ='Data Sheet'!D50 -> 5498 | E6: ='Data Sheet'!E50 -> 5375 | F6: ='Data Sheet'!F50 -> 5579 | G6: ='Data Sheet'!G50 -> 6135 | H6: ='Data Sheet'!H50 -> 7476 | I6: ='Data Sheet'!I50 -> 7027 | ... K6: ='Data Sheet'!K50 -> 8464
A7: Other Income | B7: ='Data Sheet'!B44 -> 194 | C7: ='Data Sheet'!C44 -> 242 | D7: ='Data Sheet'!D44 -> 164 | E7: ='Data Sheet'!E44 -> -189 | F7: ='Data Sheet'!F44 -> 50 | G7: ='Data Sheet'!G44 -> 186 | H7: ='Data Sheet'!H44 -> 350 | I7: ='Data Sheet'!I44 -> 284 | ... K7: ='Data Sheet'!K44 -> 18229
A8: Depreciation | B8: ='Data Sheet'!B45 -> 2059 | C8: ='Data Sheet'!C45 -> 2194 | D8: ='Data Sheet'!D45 -> 2209 | E8: ='Data Sheet'!E45 -> 2267 | F8: ='Data Sheet'!F45 -> 2336 | G8: ='Data Sheet'!G45 -> 2497 | H8: ='Data Sheet'!H45 -> 2537 | I8: ='Data Sheet'!I45 -> 2554 | ... K8: ='Data Sheet'!K45 -> 2148
A9: Interest | B9: ='Data Sheet'!B46 -> 1996 | C9: ='Data Sheet'!C46 -> 2062 | D9: ='Data Sheet'!D46 -> 2073 | E9: ='Data Sheet'!E46 -> 2130 | F9: ='Data Sheet'!F46 -> 2115 | G9: ='Data Sheet'!G46 -> 2094 | H9: ='Data Sheet'!H46 -> 2217 | I9: ='Data Sheet'!I46 -> 2413 | ... K9: ='Data Sheet'!K46 -> 2168
A10: Profit before tax | B10: ='Data Sheet'!B47 -> 3303 | C10: ='Data Sheet'!C47 -> 2012 | D10: ='Data Sheet'!D47 -> 1380 | E10: ='Data Sheet'!E47 -> 789 | F10: ='Data Sheet'!F47 -> 1178 | G10: ='Data Sheet'!G47 -> 1730 | H10: ='Data Sheet'!H47 -> 3072 | I10: ='Data Sheet'!I47 -> 2344 | ... K10: ='Data Sheet'!K47 -> 22377
A11: Tax | B11: ='Data Sheet'!B48 -> 853 | C11: ='Data Sheet'!C48 -> 690 | D11: ='Data Sheet'!D48 -> 513 | E11: ='Data Sheet'!E48 -> 385 | F11: ='Data Sheet'!F48 -> 459 | G11: ='Data Sheet'!G48 -> 229 | H11: ='Data Sheet'!H48 -> 863 | I11: ='Data Sheet'!I48 -> 698 | ... K11: ='Data Sheet'!K48 -> 3134
A12: Net profit | B12: ='Data Sheet'!B49 -> 2415 | C12: ='Data Sheet'!C49 -> 1299 | D12: ='Data Sheet'!D49 -> 845 | E12: ='Data Sheet'!E49 -> 439 | F12: ='Data Sheet'!F49 -> 717 | G12: ='Data Sheet'!G49 -> 1503 | H12: ='Data Sheet'!H49 -> 2184 | I12: ='Data Sheet'!I49 -> 1623 | ... K12: ='Data Sheet'!K49 -> 16370
A14: OPM | B14: =IF(B4>0,B6/B4,"") -> 0.17081545 | C14: =IF(C4>0,C6/C4,"") -> 0.13023839 | D14: =IF(D4>0,D6/D4,"") -> 0.12803018 | E14: =IF(E4>0,E6/E4,"") -> 0.13544502 | F14: =IF(F4>0,F6/F4,"") -> 0.1348301 | G14: =IF(G4>0,G6/G4,"") -> 0.13688391 | H14: =IF(H4>0,H6/H4,"") -> 0.17326813 | I14: =IF(I4>0,I6/I4,"") -> 0.15562987 | ... K14: =IF(K4>0,K6/K4,"") -> 0.1653771

Sheet Balance Sheet
A1: ='Profit & Loss'!A1 -> JSW STEEL LTD | E1: =UPDATE -> JSW STEEL LTD | J1: SCREENER.IN
A3: Narration | B3: ='Data Sheet'!B56 -> 42825 | C3: ='Data Sheet'!C56 -> 43190 | D3: ='Data Sheet'!D56 -> 43555 | E3: ='Data Sheet'!E56 -> 43921 | F3: ='Data Sheet'!F56 -> 44286 | G3: ='Data Sheet'!G56 -> 44651 | H3: ='Data Sheet'!H56 -> 45016 | I3: ='Data Sheet'!I56 -> 45382 | ... K3: ='Data Sheet'!K56 -> 46112
A4: Equity Share Capital | B4: ='Data Sheet'!B57 -> 301 | C4: ='Data Sheet'!C57 -> 302 | D4: ='Data Sheet'!D57 -> 301 | E4: ='Data Sheet'!E57 -> 301 | F4: ='Data Sheet'!F57 -> 302 | G4: ='Data Sheet'!G57 -> 301 | H4: ='Data Sheet'!H57 -> 301 | I4: ='Data Sheet'!I57 -> 305 | ... K4: ='Data Sheet'!K57 -> 305
A5: Reserves | B5: ='Data Sheet'!B58 -> 22346 | C5: ='Data Sheet'!C58 -> 27696 | D5: ='Data Sheet'!D58 -> 34494 | E5: ='Data Sheet'!E58 -> 36298 | F5: ='Data Sheet'!F58 -> 45308 | G5: ='Data Sheet'!G58 -> 66996 | H5: ='Data Sheet'!H58 -> 65394 | I5: ='Data Sheet'!I58 -> 77364 | ... K5: ='Data Sheet'!K58 -> 99748
A6: Borrowings | B6: ='Data Sheet'!B59 -> 43334 | C6: ='Data Sheet'!C59 -> 39393 | D6: ='Data Sheet'!D59 -> 47396 | E6: ='Data Sheet'!E59 -> 61423 | F6: ='Data Sheet'!F59 -> 66727 | G6: ='Data Sheet'!G59 -> 72237 | H6: ='Data Sheet'!H59 -> 80853 | I6: ='Data Sheet'!I59 -> 87984 | ... K6: ='Data Sheet'!K59 -> 99310
A7: Other Liabilities | B7: ='Data Sheet'!B60 -> 22024 | C7: ='Data Sheet'!C60 -> 24579 | D7: ='Data Sheet'!D60 -> 32606 | E7: ='Data Sheet'!E60 -> 33798 | F7: ='Data Sheet'!F60 -> 34826 | G7: ='Data Sheet'!G60 -> 56951 | H7: ='Data Sheet'!H60 -> 63991 | I7: ='Data Sheet'!I60 -> 62245 | ... K7: ='Data Sheet'!K60 -> 70313
A8: Total | B8: ='Data Sheet'!B61 -> 88005 | C8: ='Data Sheet'!C61 -> 91970 | D8: ='Data Sheet'!D61 -> 114797 | E8: ='Data Sheet'!E61 -> 131820 | F8: ='Data Sheet'!F61 -> 147163 | G8: ='Data Sheet'!G61 -> 196485 | H8: ='Data Sheet'!H61 -> 210539 | I8: ='Data Sheet'!I61 -> 227898 | ... K8: ='Data Sheet'!K61 -> 269676
A10: Net Block | B10: ='Data Sheet'!B62 -> 58730 | C10: ='Data Sheet'!C62 -> 57848 | D10: ='Data Sheet'!D62 -> 62644 | E10: ='Data Sheet'!E62 -> 62085 | F10: ='Data Sheet'!F62 -> 64917 | G10: ='Data Sheet'!G62 -> 99880 | H10: ='Data Sheet'!H62 -> 104452 | I10: ='Data Sheet'!I62 -> 112461 | ... K10: ='Data Sheet'!K62 -> 117552
A11: Capital Work in Progress | B11: ='Data Sheet'!B63 -> 4363 | C11: ='Data Sheet'!C63 -> 5950 | D11: ='Data Sheet'!D63 -> 11889 | E11: ='Data Sheet'!E63 -> 27191 | F11: ='Data Sheet'!F63 -> 32566 | G11: ='Data Sheet'!G63 -> 16905 | H11: ='Data Sheet'!H63 -> 22166 | I11: ='Data Sheet'!I63 -> 29676 | ... K11: ='Data Sheet'!K63 -> 21892
A12: Investments | B12: ='Data Sheet'!B64 -> 1366 | C12: ='Data Sheet'!C64 -> 1469 | D12: ='Data Sheet'!D64 -> 1894 | E12: ='Data Sheet'!E64 -> 1259 | F12: ='Data Sheet'!F64 -> 7427 | G12: ='Data Sheet'!G64 -> 4940 | H12: ='Data Sheet'!H64 -> 4806 | I12: ='Data Sheet'!I64 -> 7246 | ... K12: ='Data Sheet'!K64 -> 10218
A13: Other Assets | B13: ='Data Sheet'!B65 -> 23546 | C13: ='Data Sheet'!C65 -> 26703 | D13: ='Data Sheet'!D65 -> 38370 | E13: ='Data Sheet'!E65 -> 41285 | F13: ='Data Sheet'!F65 -> 42253 | G13: ='Data Sheet'!G65 -> 74760 | H13: ='Data Sheet'!H65 -> 79115 | I13: ='Data Sheet'!I65 -> 78515 | ... K13: ='Data Sheet'!K65 -> 120014
A14: Total | B14: ='Data Sheet'!B66 -> 88005 | C14: ='Data Sheet'!C66 -> 91970 | D14: ='Data Sheet'!D66 -> 114797 | E14: ='Data Sheet'!E66 -> 131820 | F14: ='Data Sheet'!F66 -> 147163 | G14: ='Data Sheet'!G66 -> 196485 | H14: ='Data Sheet'!H66 -> 210539 | I14: ='Data Sheet'!I66 -> 227898 | ... K14: ='Data Sheet'!K66 -> 269676
A16: Working Capital | B16: =B13-B7 -> 1522 | C16: =C13-C7 -> 2124 | D16: =D13-D7 -> 5764 | E16: =E13-E7 -> 7487 | F16: =F13-F7 -> 7427 | G16: =G13-G7 -> 17809 | H16: =H13-H7 -> 15124 | I16: =I13-I7 -> 16270 | ... K16: =K13-K7 -> 49701
A17: Debtors | B17: ='Data Sheet'!B67 -> 4149 | C17: ='Data Sheet'!C67 -> 4704 | D17: ='Data Sheet'!D67 -> 7160 | E17: ='Data Sheet'!E67 -> 4505 | F17: ='Data Sheet'!F67 -> 4486 | G17: ='Data Sheet'!G67 -> 7457 | H17: ='Data Sheet'!H67 -> 7134 | I17: ='Data Sheet'!I67 -> 7548 | ... K17: ='Data Sheet'!K67 -> 11260
A18: Inventory | B18: ='Data Sheet'!B68 -> 11395 | C18: ='Data Sheet'!C68 -> 12594 | D18: ='Data Sheet'!D68 -> 14548 | E18: ='Data Sheet'!E68 -> 13773 | F18: ='Data Sheet'!F68 -> 14249 | G18: ='Data Sheet'!G68 -> 33787 | H18: ='Data Sheet'!H68 -> 33135 | I18: ='Data Sheet'!I68 -> 37815 | ... K18: ='Data Sheet'!K68 -> 32765
A20: Debtor Days | B20: =IF('Profit & Loss'!B4>0,'Balance Sheet'!B17/('Profit & Loss'!B4/365),0) -> 27.235181 | C20: =IF('Profit & Loss'!C4>0,'Balance Sheet'!C17/('Profit & Loss'!C4/365),0) -> 23.868878 | D20: =IF('Profit & Loss'!D4>0,'Balance Sheet'!D17/('Profit & Loss'!D4/365),0) -> 30.834031 | E20: =IF('Profit & Loss'!E4>0,'Balance Sheet'!E17/('Profit & Loss'!E4/365),0) -> 22.424856 | F20: =IF('Profit & Loss'!F4>0,'Balance Sheet'!F17/('Profit & Loss'!F4/365),0) -> 20.508649 | G20: =IF('Profit & Loss'!G4>0,'Balance Sheet'!G17/('Profit & Loss'!G4/365),0) -> 18.595248 | H20: =IF('Profit & Loss'!H4>0,'Balance Sheet'!H17/('Profit & Loss'!H4/365),0) -> 15.689986 | I20: =IF('Profit & Loss'!I4>0,'Balance Sheet'!I17/('Profit & Loss'!I4/365),0) -> 15.742432 | ... K20: =IF('Profit & Loss'!K4>0,'Balance Sheet'!K17/('Profit & Loss'!K4/365),0) -> 22.159379
A21: Inventory Turnover | B21: =IF('Balance Sheet'!B18>0,'Profit & Loss'!B4/'Balance Sheet'!B18,0) -> 4.8796841 | C21: =IF('Balance Sheet'!C18>0,'Profit & Loss'!C4/'Balance Sheet'!C18,0) -> 5.7116881 | D21: =IF('Balance Sheet'!D18>0,'Profit & Loss'!D4/'Balance Sheet'!D18,0) -> 5.8260242 | E21: =IF('Balance Sheet'!E18>0,'Profit & Loss'!E4/'Balance Sheet'!E18,0) -> 5.3238946 | F21: =IF('Balance Sheet'!F18>0,'Profit & Loss'!F4/'Balance Sheet'!F18,0) -> 5.60313 | G21: =IF('Balance Sheet'!G18>0,'Profit & Loss'!G4/'Balance Sheet'!G18,0) -> 4.3321692 | H21: =IF('Balance Sheet'!H18>0,'Profit & Loss'!H4/'Balance Sheet'!H18,0) -> 5.0086012 | I21: =IF('Balance Sheet'!I18>0,'Profit & Loss'!I4/'Balance Sheet'!I18,0) -> 4.6279519 | ... K21: =IF('Balance Sheet'!K18>0,'Profit & Loss'!K4/'Balance Sheet'!K18,0) -> 5.6606135
A23: Return on Equity | B23: =IF(SUM('Balance Sheet'!B4:B5)>0,'Profit & Loss'!B12/SUM('Balance Sheet'!B4:B5),"") -> 0.15556144 | C23: =IF(SUM('Balance Sheet'!C4:C5)>0,'Profit & Loss'!C12/SUM('Balance Sheet'!C4:C5),"") -> 0.22194442 | D23: =IF(SUM('Balance Sheet'!D4:D5)>0,'Profit & Loss'!D12/SUM('Balance Sheet'!D4:D5),"") -> 0.21954304 | E23: =IF(SUM('Balance Sheet'!E4:E5)>0,'Profit & Loss'!E12/SUM('Balance Sheet'!E4:E5),"") -> 0.1101123 | F23: =IF(SUM('Balance Sheet'!F4:F5)>0,'Profit & Loss'!F12/SUM('Balance Sheet'!F4:F5),"") -> 0.17344881 | G23: =IF(SUM('Balance Sheet'!G4:G5)>0,'Profit & Loss'!G12/SUM('Balance Sheet'!G4:G5),"") -> 0.30707164 | H23: =IF(SUM('Balance Sheet'!H4:H5)>0,'Profit & Loss'!H12/SUM('Balance Sheet'!H4:H5),"") -> 0.063079382 | I23: =IF(SUM('Balance Sheet'!I4:I5)>0,'Profit & Loss'!I12/SUM('Balance Sheet'!I4:I5),"") -> 0.11345582 | ... K23: =IF(SUM('Balance Sheet'!K4:K5)>0,'Profit & Loss'!K12/SUM('Balance Sheet'!K4:K5),"") -> 0.22304179
A24: Return on Capital Emp | C24: =IF((B4+B5+B6+C4+C5+C6)>0,('Profit & Loss'!C10+'Profit & Loss'!C9)*2/(B4+B5+B6+C4+C5+C6),"") -> 0.17023063 | D24: =IF((C4+C5+C6+D4+D5+D6)>0,('Profit & Loss'!D10+'Profit & Loss'!D9)*2/(C4+C5+C6+D4+D5+D6),"") -> 0.20169539 | E24: =IF((D4+D5+D6+E4+E5+E6)>0,('Profit & Loss'!E10+'Profit & Loss'!E9)*2/(D4+D5+D6+E4+E5+E6),"") -> 0.080771088 | F24: =IF((E4+E5+E6+F4+F5+F6)>0,('Profit & Loss'!F10+'Profit & Loss'!F9)*2/(E4+E5+E6+F4+F5+F6),"") -> 0.15185469 | G24: =IF((F4+F5+F6+G4+G5+G6)>0,('Profit & Loss'!G10+'Profit & Loss'!G9)*2/(F4+F5+F6+G4+G5+G6),"") -> 0.2756411 | H24: =IF((G4+G5+G6+H4+H5+H6)>0,('Profit & Loss'!H10+'Profit & Loss'!H9)*2/(G4+G5+G6+H4+H5+H6),"") -> 0.087786019 | I24: =IF((H4+H5+H6+I4+I5+I6)>0,('Profit & Loss'!I10+'Profit & Loss'!I9)*2/(H4+H5+H6+I4+I5+I6),"") -> 0.13763569 | J24: =IF((I4+I5+I6+J4+J5+J6)>0,('Profit & Loss'!J10+'Profit & Loss'!J9)*2/(I4+I5+I6+J4+J5+J6),"") -> 0.078446995 | K24: =IF((J4+J5+J6+K4+K5+K6)>0,('Profit & Loss'!K10+'Profit & Loss'!K9)*2/(J4+J5+J6+K4+K5+K6),"") -> 0.20312968

Sheet Cash Flow
A1: ='Balance Sheet'!A1 -> JSW STEEL LTD | E1: =UPDATE -> JSW STEEL LTD | J1: SCREENER.IN
A3: Narration | B3: ='Data Sheet'!B81 -> 42825 | C3: ='Data Sheet'!C81 -> 43190 | D3: ='Data Sheet'!D81 -> 43555 | E3: ='Data Sheet'!E81 -> 43921 | F3: ='Data Sheet'!F81 -> 44286 | G3: ='Data Sheet'!G81 -> 44651 | H3: ='Data Sheet'!H81 -> 45016 | I3: ='Data Sheet'!I81 -> 45382 | ... K3: ='Data Sheet'!K81 -> 46112
A4: Cash from Operating Activity | B4: ='Data Sheet'!B82 -> 7888 | C4: ='Data Sheet'!C82 -> 12379 | D4: ='Data Sheet'!D82 -> 14633 | E4: ='Data Sheet'!E82 -> 12785 | F4: ='Data Sheet'!F82 -> 18831 | G4: ='Data Sheet'!G82 -> 26270 | H4: ='Data Sheet'!H82 -> 23323 | I4: ='Data Sheet'!I82 -> 12078 | ... K4: ='Data Sheet'!K82 -> 25152
A5: Cash from Investing Activity | B5: ='Data Sheet'!B83 -> -5094 | C5: ='Data Sheet'!C83 -> -4529 | D5: ='Data Sheet'!D83 -> -11387 | E5: ='Data Sheet'!E83 -> -19589 | F5: ='Data Sheet'!F83 -> -9410 | G5: ='Data Sheet'!G83 -> -14748 | H5: ='Data Sheet'!H83 -> -10730 | I5: ='Data Sheet'!I83 -> -14467 | ... K5: ='Data Sheet'!K83 -> 18690
A6: Cash from Financing Activity | B6: ='Data Sheet'!B84 -> -2710 | C6: ='Data Sheet'!C84 -> -8185 | D6: ='Data Sheet'!D84 -> 1753 | E6: ='Data Sheet'!E84 -> 5189 | F6: ='Data Sheet'!F84 -> -1444 | G6: ='Data Sheet'!G84 -> -14657 | H6: ='Data Sheet'!H84 -> -5977 | I6: ='Data Sheet'!I84 -> -5005 | ... K6: ='Data Sheet'!K84 -> -16111
A7: Net Cash Flow | B7: ='Data Sheet'!B85 -> 84 | C7: ='Data Sheet'!C85 -> -335 | D7: ='Data Sheet'!D85 -> 4999 | E7: ='Data Sheet'!E85 -> -1615 | F7: ='Data Sheet'!F85 -> 7977 | G7: ='Data Sheet'!G85 -> -3135 | H7: ='Data Sheet'!H85 -> 6616 | I7: ='Data Sheet'!I85 -> -7394 | ... K7: ='Data Sheet'!K85 -> 27731

Sheet Customization
A1: How to use it?
A3: You can customize this workbook as you want.
B4: You can add custom formating, add conditional formating, add your own formulas… do ANYTHING.
B5: Please don't edit the "Data Sheet" only.
A7: After customization, you can upload this back on Screener.
B8: Upload on: | C8: https://www.screener.in/excel/
A10: Download your customized workbooks now onwards.
B11: Now whenever you will "Export to excel" from Screener, it will export your customized file.
A14: TESTING:
B15: This is a testing feature currently.
B16: You can report any formula errors on the worksheet at: support@screener.in

Sheet Historical
B2: ="Financial Statement - "&'Data Sheet'!B1 -> Financial Statement - JSW STEEL LTD
B4: Particulars | C4: ='Data Sheet'!B16 -> 42825 | D4: ='Data Sheet'!C16 -> 43190 | E4: ='Data Sheet'!D16 -> 43555 | F4: ='Data Sheet'!E16 -> 43921 | G4: ='Data Sheet'!F16 -> 44286 | H4: ='Data Sheet'!G16 -> 44651 | I4: ='Data Sheet'!H16 -> 45016 | J4: ='Data Sheet'!I16 -> 45382 | ... L4: ='Data Sheet'!K16 -> 46112 | M4: LTM
A5: # | B5: income statement
B7: sales | C7: ='Data Sheet'!B17 -> 55604 | D7: ='Data Sheet'!C17 -> 71933 | E7: ='Data Sheet'!D17 -> 84757 | F7: ='Data Sheet'!E17 -> 73326 | G7: ='Data Sheet'!F17 -> 79839 | H7: ='Data Sheet'!G17 -> 146371 | I7: ='Data Sheet'!H17 -> 165960 | J7: ='Data Sheet'!I17 -> 175006 | ... L7: ='Data Sheet'!K17 -> 185470 | M7: =IFERROR(SUM('Data Sheet'!H42:K42),0) -> 185470
B8: sales growth | D8: =D7/C7-1 -> 0.29366592 | E8: =E7/D7-1 -> 0.17827701 | F8: =F7/E7-1 -> -0.13486792 | G8: =G7/F7-1 -> 0.088822519 | H8: =H7/G7-1 -> 0.83332707 | I8: =I7/H7-1 -> 0.13383116 | J8: =J7/I7-1 -> 0.05450711 | K8: =K7/J7-1 -> -0.035324503 | ... M8: =M7/L7-1 -> 0
B10: COGS | C10: =IFERROR(SUM('Data Sheet'!B18,'Data Sheet'!B20:B22)-1*'Data Sheet'!B19,0) -> 41733 | D10: =IFERROR(SUM('Data Sheet'!C18,'Data Sheet'!C20:C22)-1*'Data Sheet'!C19,0) -> 55278 | E10: =IFERROR(SUM('Data Sheet'!D18,'Data Sheet'!D20:D22)-1*'Data Sheet'!D19,0) -> 62906 | F10: =IFERROR(SUM('Data Sheet'!E18,'Data Sheet'!E20:E22)-1*'Data Sheet'!E19,0) -> 58084 | G10: =IFERROR(SUM('Data Sheet'!F18,'Data Sheet'!F20:F22)-1*'Data Sheet'!F19,0) -> 57246 | H10: =IFERROR(SUM('Data Sheet'!G18,'Data Sheet'!G20:G22)-1*'Data Sheet'!G19,0) -> 103778 | I10: =IFERROR(SUM('Data Sheet'!H18,'Data Sheet'!H20:H22)-1*'Data Sheet'!H19,0) -> 140925 | J10: =IFERROR(SUM('Data Sheet'!I18,'Data Sheet'!I20:I22)-1*'Data Sheet'!I19,0) -> 141101 | ... L10: =IFERROR(SUM('Data Sheet'!K18,'Data Sheet'!K20:K22)-1*'Data Sheet'!K19,0) -> 118028 | M10: =IFERROR(SUM('Data Sheet'!H43:K43),0) -> 156124
B11: cogs % sales | C11: =C10/C7 -> 0.75053953 | D11: =D10/D7 -> 0.7684651 | E11: =E10/E7 -> 0.74219239 | F11: =F10/F7 -> 0.79213376 | G11: =G10/G7 -> 0.717018 | H11: =H10/H7 -> 0.70900657 | I11: =I10/I7 -> 0.8491504 | J11: =J10/J7 -> 0.80626379 | ... M11: =M10/M7 -> 0.84177495
B13: gross profit | C13: =IFERROR(SUM(C7)-C10,0) -> 13871 | D13: =IFERROR(SUM(D7)-D10,0) -> 16655 | E13: =IFERROR(SUM(E7)-E10,0) -> 21851 | F13: =IFERROR(SUM(F7)-F10,0) -> 15242 | G13: =IFERROR(SUM(G7)-G10,0) -> 22593 | H13: =IFERROR(SUM(H7)-H10,0) -> 42593 | I13: =IFERROR(SUM(I7)-I10,0) -> 25035 | J13: =IFERROR(SUM(J7)-J10,0) -> 33905 | ... M13: =IFERROR(SUM(M7)-M10,0) -> 29346
B14: gross profit as % sales | C14: =C13/C7 -> 0.24946047 | D14: =D13/D7 -> 0.2315349 | E14: =E13/E7 -> 0.25780761 | F14: =F13/F7 -> 0.20786624 | G14: =G13/G7 -> 0.282982 | H14: =H13/H7 -> 0.29099343 | I14: =I13/I7 -> 0.1508496 | J14: =J13/J7 -> 0.19373621 | ... M14: =M13/M7 -> 0.15822505
B16: SG&A | C16: =IFERROR(SUM('Data Sheet'!B23,'Data Sheet'!B24),0) -> 1563 | D16: =IFERROR(SUM('Data Sheet'!C23,'Data Sheet'!C24),0) -> 1739 | E16: =IFERROR(SUM('Data Sheet'!D23,'Data Sheet'!D24),0) -> 2921 | F16: =IFERROR(SUM('Data Sheet'!E23,'Data Sheet'!E24),0) -> 3429 | G16: =IFERROR(SUM('Data Sheet'!F23,'Data Sheet'!F24),0) -> 2415 | H16: =IFERROR(SUM('Data Sheet'!G23,'Data Sheet'!G24),0) -> 3479 | I16: =IFERROR(SUM('Data Sheet'!H23,'Data Sheet'!H24),0) -> 6565 | J16: =IFERROR(SUM('Data Sheet'!I23,'Data Sheet'!I24),0) -> 5748 | ... L16: =IFERROR(SUM('Data Sheet'!K23,'Data Sheet'!K24),0) -> 38096 | M16: =IFERROR(SUM('Data Sheet'!B23,'Data Sheet'!B24),0) -> 1563
B17: SG&A as % of sales | C17: =C16/C7 -> 0.028109489 | D17: =D16/D7 -> 0.024175274 | E17: =E16/E7 -> 0.03446323 | F17: =F16/F7 -> 0.046763767 | G17: =G16/G7 -> 0.030248375 | H17: =H16/H7 -> 0.023768369 | I17: =I16/I7 -> 0.039557725 | J17: =J16/J7 -> 0.032844588 | ... M17: =M16/M7 -> 0.0084272389
B19: EBITDA | C19: =IFERROR(C13-C16,0) -> 12308 | D19: =IFERROR(D13-D16,0) -> 14916 | E19: =IFERROR(E13-E16,0) -> 18930 | F19: =IFERROR(F13-F16,0) -> 11813 | G19: =IFERROR(G13-G16,0) -> 20178 | H19: =IFERROR(H13-H16,0) -> 39114 | I19: =IFERROR(I13-I16,0) -> 18470 | J19: =IFERROR(J13-J16,0) -> 28157 | ... M19: =IFERROR(M13-M16,0) -> 27783
B20: ebitda as % of sales | C20: =C19/C7 -> 0.22135098 | D20: =D19/D7 -> 0.20735963 | E20: =E19/E7 -> 0.22334438 | F20: =F19/F7 -> 0.16110247 | G20: =G19/G7 -> 0.25273363 | H20: =H19/H7 -> 0.26722507 | I20: =I19/I7 -> 0.11129188 | J20: =J19/J7 -> 0.16089163 | ... M20: =M19/M7 -> 0.14979781
B22: Interest | C22: =IFERROR('Data Sheet'!B27,0) -> 3768 | D22: =IFERROR('Data Sheet'!C27,0) -> 3701 | E22: =IFERROR('Data Sheet'!D27,0) -> 3917 | F22: =IFERROR('Data Sheet'!E27,0) -> 4265 | G22: =IFERROR('Data Sheet'!F27,0) -> 3957 | H22: =IFERROR('Data Sheet'!G27,0) -> 4968 | I22: =IFERROR('Data Sheet'!H27,0) -> 6902 | J22: =IFERROR('Data Sheet'!I27,0) -> 8105 | ... L22: =IFERROR('Data Sheet'!K27,0) -> 9102 | M22: =IFERROR(SUM('Data Sheet'!H46:K46),0) -> 9102
B23: interset as % of sale | C23: =C22/C7 -> 0.067764909 | D23: =D22/D7 -> 0.051450655 | E23: =E22/E7 -> 0.046214472 | F23: =F22/F7 -> 0.058164907 | G23: =G22/G7 -> 0.049562244 | H23: =H22/H7 -> 0.03394115 | I23: =I22/I7 -> 0.041588335 | J23: =J22/J7 -> 0.046312698 | ... M23: =M22/M7 -> 0.049075322
B25: Depriciation | C25: =IFERROR('Data Sheet'!B26,0) -> 3430 | D25: =IFERROR('Data Sheet'!C26,0) -> 3387 | E25: =IFERROR('Data Sheet'!D26,0) -> 4041 | F25: =IFERROR('Data Sheet'!E26,0) -> 4246 | G25: =IFERROR('Data Sheet'!F26,0) -> 4679 | H25: =IFERROR('Data Sheet'!G26,0) -> 6001 | I25: =IFERROR('Data Sheet'!H26,0) -> 7474 | J25: =IFERROR('Data Sheet'!I26,0) -> 8172 | ... L25: =IFERROR('Data Sheet'!K26,0) -> 9601 | M25: =IFERROR(SUM('Data Sheet'!H45:K45),0) -> 9601
B26: depriciation % of slaes | C26: =C25/C7 -> 0.06168621 | D26: =D25/D7 -> 0.047085482 | E26: =E25/E7 -> 0.047677478 | F26: =F25/F7 -> 0.057905791 | G26: =G25/G7 -> 0.058605443 | H26: =H25/H7 -> 0.040998558 | I26: =I25/I7 -> 0.045034948 | J26: =J25/J7 -> 0.046695542 | ... M26: =M25/M7 -> 0.051765784
B28: EBT | C28: =IFERROR(C19-C22-C25,0) -> 5110 | D28: =IFERROR(D19-D22-D25,0) -> 7828 | E28: =IFERROR(E19-E22-E25,0) -> 10972 | F28: =IFERROR(F19-F22-F25,0) -> 3302 | G28: =IFERROR(G19-G22-G25,0) -> 11542 | H28: =IFERROR(H19-H22-H25,0) -> 28145 | I28: =IFERROR(I19-I22-I25,0) -> 4094 | J28: =IFERROR(J19-J22-J25,0) -> 11880 | ... M28: =IFERROR(M19-M22-M25,0) -> 9080
B29: ebt % of sales | C29: =C28/C7 -> 0.091899863 | D29: =D28/D7 -> 0.10882349 | E29: =E28/E7 -> 0.12945243 | F29: =F28/F7 -> 0.045031776 | G29: =G28/G7 -> 0.14456594 | H29: =H28/H7 -> 0.19228536 | I29: =I28/I7 -> 0.024668595 | J29: =J28/J7 -> 0.067883387 | ... L29: =L28/L7 -> 0.057383943
B31: TAX | C31: =IFERROR('Data Sheet'!B29,0) -> 1674 | D31: =IFERROR('Data Sheet'!C29,0) -> 1538 | E31: =IFERROR('Data Sheet'!D29,0) -> 3644 | F31: =IFERROR('Data Sheet'!E29,0) -> -906 | G31: =IFERROR('Data Sheet'!F29,0) -> 4142 | H31: =IFERROR('Data Sheet'!G29,0) -> 8807 | I31: =IFERROR('Data Sheet'!H29,0) -> 1516 | J31: =IFERROR('Data Sheet'!I29,0) -> 4407 | ... L31: =IFERROR('Data Sheet'!K29,0) -> 3742 | M31: =IFERROR(SUM('Data Sheet'!H48:K48),0) -> 3742
B32: effective tax rate % of EBT | C32: =C31/C28 -> 0.32759295 | D32: =D31/D28 -> 0.1964742 | E32: =E31/E28 -> 0.33211812 | F32: =F31/F28 -> -0.27437916 | G32: =G31/G28 -> 0.35886328 | H32: =H31/H28 -> 0.31291526 | I32: =I31/I28 -> 0.370298 | J32: =J31/J28 -> 0.3709596 | ... M32: =M31/M28 -> 0.41211454
B34: Net Profit | C34: =IFERROR(C28-C31,0) -> 3436 | D34: =IFERROR(D28-D31,0) -> 6290 | E34: =IFERROR(E28-E31,0) -> 7328 | F34: =IFERROR(F28-F31,0) -> 4208 | G34: =IFERROR(G28-G31,0) -> 7400 | H34: =IFERROR(H28-H31,0) -> 19338 | I34: =IFERROR(I28-I31,0) -> 2578 | J34: =IFERROR(J28-J31,0) -> 7473 | ... M34: =IFERROR(M28-M31,0) -> 5338
B35: net margin | C35: =C34/C7 -> 0.061794116 | D35: =D34/D7 -> 0.087442481 | E35: =E34/E7 -> 0.086458936 | F35: =F34/F7 -> 0.057387557 | G35: =G34/G7 -> 0.092686532 | H35: =H34/H7 -> 0.13211633 | I35: =I34/I7 -> 0.015533864 | J35: =J34/J7 -> 0.042701393 | ... M35: =M34/M7 -> 0.028780935
B37: Adjusted Equity Shares in Cr | C37: 288.72 | D37: 288.73 | E37: 288.73 | F37: 288.73 | G37: 308.9 | H37: 332.03 | I37: 332.07 | J37: 332.13 | K37: 332.37 | L37: 368.13
B39: EPS | C39: =IFERROR(C34/C37,0) -> 11.900804 | D39: =IFERROR(D34/D37,0) -> 21.785059 | E39: =IFERROR(E34/E37,0) -> 25.380113 | F39: =IFERROR(F34/F37,0) -> 14.57417 | G39: =IFERROR(G34/G37,0) -> 23.955973 | H39: =IFERROR(H34/H37,0) -> 58.241725 | I39: =IFERROR(I34/I37,0) -> 7.7634234 | J39: =IFERROR(J34/J37,0) -> 22.500226 | ... L39: =IFERROR(L34/L37,0) -> 18.746095
B40: eps growth % | D40: =IFERROR(D39/C39-1,0) -> 0.83055359 | E40: =IFERROR(E39/D39-1,0) -> 0.16502385 | F40: =IFERROR(F39/E39-1,0) -> -0.42576419 | G40: =IFERROR(G39/F39-1,0) -> 0.64372814 | H40: =IFERROR(H39/G39-1,0) -> 1.4311985 | I40: =IFERROR(I39/H39-1,0) -> -0.86670341 | J40: =IFERROR(J39/I39-1,0) -> 1.8982351 | K40: =IFERROR(K39/J39-1,0) -> -0.54295037 | L40: =IFERROR(L39/K39-1,0) -> 0.82289047
B42: dividend per share | C42: =IFERROR('Data Sheet'!B31/C37,0) -> 2.3456983 | D42: =IFERROR('Data Sheet'!C31/D37,0) -> 3.3470717 | E42: =IFERROR('Data Sheet'!D31/E37,0) -> 4.2742354 | F42: =IFERROR('Data Sheet'!E31/F37,0) -> 2.0849929 | G42: =IFERROR('Data Sheet'!F31/G37,0) -> 6.3548074 | H42: =IFERROR('Data Sheet'!G31/H37,0) -> 15.728549 | I42: =IFERROR('Data Sheet'!H31/I37,0) -> 3.0818803 | J42: =IFERROR('Data Sheet'!I31/J37,0) -> 6.7037004 | ... L42: =IFERROR('Data Sheet'!K31/L37,0) -> 5.8824328
B43: dividend payout ratio % | C43: =IFERROR(C42/C39,0) -> 0.19710419 | D43: =IFERROR(D42/D39,0) -> 0.1536407 | E43: =IFERROR(E42/E39,0) -> 0.16840884 | F43: =IFERROR(F42/F39,0) -> 0.14306084 | G43: =IFERROR(G42/G39,0) -> 0.26527027 | H43: =IFERROR(H42/H39,0) -> 0.27005637 | I43: =IFERROR(I42/I39,0) -> 0.3969744 | J43: =IFERROR(J42/J39,0) -> 0.29793925 | ... L43: =IFERROR(L42/L39,0) -> 0.3137951
B45: retained earning | C45: =IFERROR(IF(C39>C42,1-C43,0),0) -> 0.80289581 | D45: =IFERROR(IF(D39>D42,1-D43,0),0) -> 0.8463593 | E45: =IFERROR(IF(E39>E42,1-E43,0),0) -> 0.83159116 | F45: =IFERROR(IF(F39>F42,1-F43,0),0) -> 0.85693916 | G45: =IFERROR(IF(G39>G42,1-G43,0),0) -> 0.73472973 | H45: =IFERROR(IF(H39>H42,1-H43,0),0) -> 0.72994363 | I45: =IFERROR(IF(I39>I42,1-I43,0),0) -> 0.6030256 | J45: =IFERROR(IF(J39>J42,1-J43,0),0) -> 0.70206075 | ... L45: =IFERROR(IF(L39>L42,1-L43,0),0) -> 0.6862049
A50: # | B50: balance sheet
B52: Equity Share Capital | C52: =IFERROR('Data Sheet'!B57,0) -> 301 | D52: =IFERROR('Data Sheet'!C57,0) -> 302 | E52: =IFERROR('Data Sheet'!D57,0) -> 301 | F52: =IFERROR('Data Sheet'!E57,0) -> 301 | G52: =IFERROR('Data Sheet'!F57,0) -> 302 | H52: =IFERROR('Data Sheet'!G57,0) -> 301 | I52: =IFERROR('Data Sheet'!H57,0) -> 301 | J52: =IFERROR('Data Sheet'!I57,0) -> 305 | ... L52: =IFERROR('Data Sheet'!K57,0) -> 305
B53: Reserves | C53: =IFERROR('Data Sheet'!B58,0) -> 22346 | D53: =IFERROR('Data Sheet'!C58,0) -> 27696 | E53: =IFERROR('Data Sheet'!D58,0) -> 34494 | F53: =IFERROR('Data Sheet'!E58,0) -> 36298 | G53: =IFERROR('Data Sheet'!F58,0) -> 45308 | H53: =IFERROR('Data Sheet'!G58,0) -> 66996 | I53: =IFERROR('Data Sheet'!H58,0) -> 65394 | J53: =IFERROR('Data Sheet'!I58,0) -> 77364 | ... L53: =IFERROR('Data Sheet'!K58,0) -> 99748
B54: Borrowings | C54: =IFERROR('Data Sheet'!B59,0) -> 43334 | D54: =IFERROR('Data Sheet'!C59,0) -> 39393 | E54: =IFERROR('Data Sheet'!D59,0) -> 47396 | F54: =IFERROR('Data Sheet'!E59,0) -> 61423 | G54: =IFERROR('Data Sheet'!F59,0) -> 66727 | H54: =IFERROR('Data Sheet'!G59,0) -> 72237 | I54: =IFERROR('Data Sheet'!H59,0) -> 80853 | J54: =IFERROR('Data Sheet'!I59,0) -> 87984 | ... L54: =IFERROR('Data Sheet'!K59,0) -> 99310
B55: Other Liabilities | C55: =IFERROR('Data Sheet'!B60,0) -> 22024 | D55: =IFERROR('Data Sheet'!C60,0) -> 24579 | E55: =IFERROR('Data Sheet'!D60,0) -> 32606 | F55: =IFERROR('Data Sheet'!E60,0) -> 33798 | G55: =IFERROR('Data Sheet'!F60,0) -> 34826 | H55: =IFERROR('Data Sheet'!G60,0) -> 56951 | I55: =IFERROR('Data Sheet'!H60,0) -> 63991 | J55: =IFERROR('Data Sheet'!I60,0) -> 62245 | ... L55: =IFERROR('Data Sheet'!K60,0) -> 70313
B56: total libalitites | C56: =IFERROR('Data Sheet'!B61,0) -> 88005 | D56: =IFERROR('Data Sheet'!C61,0) -> 91970 | E56: =IFERROR('Data Sheet'!D61,0) -> 114797 | F56: =IFERROR('Data Sheet'!E61,0) -> 131820 | G56: =IFERROR('Data Sheet'!F61,0) -> 147163 | H56: =IFERROR('Data Sheet'!G61,0) -> 196485 | I56: =IFERROR('Data Sheet'!H61,0) -> 210539 | J56: =IFERROR('Data Sheet'!I61,0) -> 227898 | ... L56: =IFERROR('Data Sheet'!K61,0) -> 269676
B58: assest net block | C58: =IFERROR('Data Sheet'!B62,0) -> 58730 | D58: =IFERROR('Data Sheet'!C62,0) -> 57848 | E58: =IFERROR('Data Sheet'!D62,0) -> 62644 | F58: =IFERROR('Data Sheet'!E62,0) -> 62085 | G58: =IFERROR('Data Sheet'!F62,0) -> 64917 | H58: =IFERROR('Data Sheet'!G62,0) -> 99880 | I58: =IFERROR('Data Sheet'!H62,0) -> 104452 | J58: =IFERROR('Data Sheet'!I62,0) -> 112461 | ... L58: =IFERROR('Data Sheet'!K62,0) -> 117552
B59: Capital Work in Progress | C59: =IFERROR('Data Sheet'!B63,0) -> 4363 | D59: =IFERROR('Data Sheet'!C63,0) -> 5950 | E59: =IFERROR('Data Sheet'!D63,0) -> 11889 | F59: =IFERROR('Data Sheet'!E63,0) -> 27191 | G59: =IFERROR('Data Sheet'!F63,0) -> 32566 | H59: =IFERROR('Data Sheet'!G63,0) -> 16905 | I59: =IFERROR('Data Sheet'!H63,0) -> 22166 | J59: =IFERROR('Data Sheet'!I63,0) -> 29676 | ... L59: =IFERROR('Data Sheet'!K63,0) -> 21892
B60: Investments | C60: =IFERROR('Data Sheet'!B64,0) -> 1366 | D60: =IFERROR('Data Sheet'!C64,0) -> 1469 | E60: =IFERROR('Data Sheet'!D64,0) -> 1894 | F60: =IFERROR('Data Sheet'!E64,0) -> 1259 | G60: =IFERROR('Data Sheet'!F64,0) -> 7427 | H60: =IFERROR('Data Sheet'!G64,0) -> 4940 | I60: =IFERROR('Data Sheet'!H64,0) -> 4806 | J60: =IFERROR('Data Sheet'!I64,0) -> 7246 | ... L60: =IFERROR('Data Sheet'!K64,0) -> 10218
B61: Other Assets | C61: =IFERROR('Data Sheet'!B65-SUM('Data Sheet'!B67:B69),0) -> 6517 | D61: =IFERROR('Data Sheet'!C65-SUM('Data Sheet'!C67:C69),0) -> 8342 | E61: =IFERROR('Data Sheet'!D65-SUM('Data Sheet'!D67:D69),0) -> 10475 | F61: =IFERROR('Data Sheet'!E65-SUM('Data Sheet'!E67:E69),0) -> 11004 | G61: =IFERROR('Data Sheet'!F65-SUM('Data Sheet'!F67:F69),0) -> 10705 | H61: =IFERROR('Data Sheet'!G65-SUM('Data Sheet'!G67:G69),0) -> 16133 | I61: =IFERROR('Data Sheet'!H65-SUM('Data Sheet'!H67:H69),0) -> 18132 | J61: =IFERROR('Data Sheet'!I65-SUM('Data Sheet'!I67:I69),0) -> 20804 | ... L61: =IFERROR('Data Sheet'!K65-SUM('Data Sheet'!K67:K69),0) -> 35000
B62: total non current assest | C62: =IFERROR(SUM(C58:C61),0) -> 70976 | D62: =IFERROR(SUM(D58:D61),0) -> 73609 | E62: =IFERROR(SUM(E58:E61),0) -> 86902 | F62: =IFERROR(SUM(F58:F61),0) -> 101539 | G62: =IFERROR(SUM(G58:G61),0) -> 115615 | H62: =IFERROR(SUM(H58:H61),0) -> 137858 | I62: =IFERROR(SUM(I58:I61),0) -> 149556 | J62: =IFERROR(SUM(J58:J61),0) -> 170187 | ... L62: =IFERROR(SUM(L58:L61),0) -> 184662
B64: Receivables | C64: =IFERROR('Data Sheet'!B67,0) -> 4149 | D64: =IFERROR('Data Sheet'!C67,0) -> 4704 | E64: =IFERROR('Data Sheet'!D67,0) -> 7160 | F64: =IFERROR('Data Sheet'!E67,0) -> 4505 | G64: =IFERROR('Data Sheet'!F67,0) -> 4486 | H64: =IFERROR('Data Sheet'!G67,0) -> 7457 | I64: =IFERROR('Data Sheet'!H67,0) -> 7134 | J64: =IFERROR('Data Sheet'!I67,0) -> 7548 | ... L64: =IFERROR('Data Sheet'!K67,0) -> 11260
B65: Inventory | C65: =IFERROR('Data Sheet'!B68,0) -> 11395 | D65: =IFERROR('Data Sheet'!C68,0) -> 12594 | E65: =IFERROR('Data Sheet'!D68,0) -> 14548 | F65: =IFERROR('Data Sheet'!E68,0) -> 13773 | G65: =IFERROR('Data Sheet'!F68,0) -> 14249 | H65: =IFERROR('Data Sheet'!G68,0) -> 33787 | I65: =IFERROR('Data Sheet'!H68,0) -> 33135 | J65: =IFERROR('Data Sheet'!I68,0) -> 37815 | ... L65: =IFERROR('Data Sheet'!K68,0) -> 32765
B66: Cash & Bank | C66: =IFERROR('Data Sheet'!B69,0) -> 1485 | D66: =IFERROR('Data Sheet'!C69,0) -> 1063 | E66: =IFERROR('Data Sheet'!D69,0) -> 6187 | F66: =IFERROR('Data Sheet'!E69,0) -> 12003 | G66: =IFERROR('Data Sheet'!F69,0) -> 12813 | H66: =IFERROR('Data Sheet'!G69,0) -> 17383 | I66: =IFERROR('Data Sheet'!H69,0) -> 20714 | J66: =IFERROR('Data Sheet'!I69,0) -> 12348 | ... L66: =IFERROR('Data Sheet'!K69,0) -> 40989
B67: Total current assest | C67: =SUM(C64:C66) -> 17029 | D67: =SUM(D64:D66) -> 18361 | E67: =SUM(E64:E66) -> 27895 | F67: =SUM(F64:F66) -> 30281 | G67: =SUM(G64:G66) -> 31548 | H67: =SUM(H64:H66) -> 58627 | I67: =SUM(I64:I66) -> 60983 | J67: =SUM(J64:J66) -> 57711 | ... L67: =SUM(L64:L66) -> 85014
B69: total assest | C69: =IFERROR(SUM(C62+C67),0) -> 88005 | D69: =IFERROR(SUM(D62+D67),0) -> 91970 | E69: =IFERROR(SUM(E62+E67),0) -> 114797 | F69: =IFERROR(SUM(F62+F67),0) -> 131820 | G69: =IFERROR(SUM(G62+G67),0) -> 147163 | H69: =IFERROR(SUM(H62+H67),0) -> 196485 | I69: =IFERROR(SUM(I62+I67),0) -> 210539 | J69: =IFERROR(SUM(J62+J67),0) -> 227898 | ... L69: =IFERROR(SUM(L62+L67),0) -> 269676
B71: check | C71: =C69=C56 -> TRUE | D71: =D69=D56 -> TRUE | E71: =E69=E56 -> TRUE | F71: =F69=F56 -> TRUE | G71: =G69=G56 -> TRUE | H71: =H69=H56 -> TRUE | I71: =I69=I56 -> TRUE | J71: =J69=J56 -> TRUE | ... L71: =L69=L56 -> TRUE
A74: # | B74: cash flow statement
B75: Cash from Operating Activity | C75: =IFERROR('Data Sheet'!B82,0) -> 7888 | D75: =IFERROR('Data Sheet'!C82,0) -> 12379 | E75: =IFERROR('Data Sheet'!D82,0) -> 14633 | F75: =IFERROR('Data Sheet'!E82,0) -> 12785 | G75: =IFERROR('Data Sheet'!F82,0) -> 18831 | H75: =IFERROR('Data Sheet'!G82,0) -> 26270 | I75: =IFERROR('Data Sheet'!H82,0) -> 23323 | J75: =IFERROR('Data Sheet'!I82,0) -> 12078 | ... L75: =IFERROR('Data Sheet'!K82,0) -> 25152
B77: Cash from Investing Activity | C77: =IFERROR('Data Sheet'!B83,0) -> -5094 | D77: =IFERROR('Data Sheet'!C83,0) -> -4529 | E77: =IFERROR('Data Sheet'!D83,0) -> -11387 | F77: =IFERROR('Data Sheet'!E83,0) -> -19589 | G77: =IFERROR('Data Sheet'!F83,0) -> -9410 | H77: =IFERROR('Data Sheet'!G83,0) -> -14748 | I77: =IFERROR('Data Sheet'!H83,0) -> -10730 | J77: =IFERROR('Data Sheet'!I83,0) -> -14467 | ... L77: =IFERROR('Data Sheet'!K83,0) -> 18690
B79: Cash from Financing Activity | C79: =IFERROR('Data Sheet'!B84,0) -> -2710 | D79: =IFERROR('Data Sheet'!C84,0) -> -8185 | E79: =IFERROR('Data Sheet'!D84,0) -> 1753 | F79: =IFERROR('Data Sheet'!E84,0) -> 5189 | G79: =IFERROR('Data Sheet'!F84,0) -> -1444 | H79: =IFERROR('Data Sheet'!G84,0) -> -14657 | I79: =IFERROR('Data Sheet'!H84,0) -> -5977 | J79: =IFERROR('Data Sheet'!I84,0) -> -5005 | ... L79: =IFERROR('Data Sheet'!K84,0) -> -16111
B81: Net Cash Flow | C81: =IFERROR('Data Sheet'!B85,0) -> 84 | D81: =IFERROR('Data Sheet'!C85,0) -> -335 | E81: =IFERROR('Data Sheet'!D85,0) -> 4999 | F81: =IFERROR('Data Sheet'!E85,0) -> -1615 | G81: =IFERROR('Data Sheet'!F85,0) -> 7977 | H81: =IFERROR('Data Sheet'!G85,0) -> -3135 | I81: =IFERROR('Data Sheet'!H85,0) -> 6616 | J81: =IFERROR('Data Sheet'!I85,0) -> -7394 | ... L81: =IFERROR('Data Sheet'!K85,0) -> 27731

Sheet Common Size
B2: Common Size Statement
B5: Particulars | F5: ='Data Sheet'!B16 -> 42825 | G5: ='Data Sheet'!C16 -> 43190 | H5: ='Data Sheet'!D16 -> 43555 | I5: ='Data Sheet'!E16 -> 43921 | J5: ='Data Sheet'!F16 -> 44286 | K5: ='Data Sheet'!G16 -> 44651 | L5: ='Data Sheet'!H16 -> 45016 | M5: ='Data Sheet'!I16 -> 45382 | ... O5: ='Data Sheet'!K16 -> 46112
A6: # | B6: Income Statement
B8: ='Data Sheet'!A17 -> Sales | F8: ='Data Sheet'!B17/'Data Sheet'!B$17 -> 1 | G8: ='Data Sheet'!C17/'Data Sheet'!C$17 -> 1 | H8: ='Data Sheet'!D17/'Data Sheet'!D$17 -> 1 | I8: ='Data Sheet'!E17/'Data Sheet'!E$17 -> 1 | J8: ='Data Sheet'!F17/'Data Sheet'!F$17 -> 1 | K8: ='Data Sheet'!G17/'Data Sheet'!G$17 -> 1 | L8: ='Data Sheet'!H17/'Data Sheet'!H$17 -> 1 | M8: ='Data Sheet'!I17/'Data Sheet'!I$17 -> 1 | ... O8: ='Data Sheet'!K17/'Data Sheet'!K$17 -> 1
B9: ='Data Sheet'!A18 -> Raw Material Cost | F9: ='Data Sheet'!B18/'Data Sheet'!B$17 -> 0.53501547 | G9: ='Data Sheet'!C18/'Data Sheet'!C$17 -> 0.53912669 | H9: ='Data Sheet'!D18/'Data Sheet'!D$17 -> 0.51672428 | I9: ='Data Sheet'!E18/'Data Sheet'!E$17 -> 0.53187137 | J9: ='Data Sheet'!F18/'Data Sheet'!F$17 -> 0.4115282 | K9: ='Data Sheet'!G18/'Data Sheet'!G$17 -> 0.42953181 | L9: ='Data Sheet'!H18/'Data Sheet'!H$17 -> 0.57827187 | M9: ='Data Sheet'!I18/'Data Sheet'!I$17 -> 0.54143287 | ... O9: ='Data Sheet'!K18/'Data Sheet'!K$17 -> 0.49534696
B10: ='Data Sheet'!A19 -> Change in Inventory | F10: ='Data Sheet'!B19/'Data Sheet'!B$17 -> 0.026724696 | G10: ='Data Sheet'!C19/'Data Sheet'!C$17 -> -0.0033920454 | H10: ='Data Sheet'!D19/'Data Sheet'!D$17 -> 0.006961077 | I10: ='Data Sheet'!E19/'Data Sheet'!E$17 -> 0.0036821864 | J10: ='Data Sheet'!F19/'Data Sheet'!F$17 -> 0.004358772 | K10: ='Data Sheet'!G19/'Data Sheet'!G$17 -> 0.024601868 | L10: ='Data Sheet'!H19/'Data Sheet'!H$17 -> 0.015883345 | M10: ='Data Sheet'!I19/'Data Sheet'!I$17 -> 0.017639395 | ... O10: ='Data Sheet'!K19/'Data Sheet'!K$17 -> -0.025443468
B11: ='Data Sheet'!A20 -> Power and Fuel | F11: ='Data Sheet'!B20/'Data Sheet'!B$17 -> 0.087817423 | G11: ='Data Sheet'!C20/'Data Sheet'!C$17 -> 0.079198699 | H11: ='Data Sheet'!D20/'Data Sheet'!D$17 -> 0.083214366 | I11: ='Data Sheet'!E20/'Data Sheet'!E$17 -> 0.085535826 | J11: ='Data Sheet'!F20/'Data Sheet'!F$17 -> 0.074963364 | K11: ='Data Sheet'!G20/'Data Sheet'!G$17 -> 0.077125933 | L11: ='Data Sheet'!H20/'Data Sheet'!H$17 -> 0.10515787 | M11: ='Data Sheet'!I20/'Data Sheet'!I$17 -> 0.086437036 | ... O11: ='Data Sheet'!K20/'Data Sheet'!K$17 -> 0.08708686
B12: ='Data Sheet'!A21 -> Other Mfr. Exp | F12: ='Data Sheet'!B21/'Data Sheet'!B$17 -> 0.123858 | G12: ='Data Sheet'!C21/'Data Sheet'!C$17 -> 0.1211266 | H12: ='Data Sheet'!D21/'Data Sheet'!D$17 -> 0.11984851 | I12: ='Data Sheet'!E21/'Data Sheet'!E$17 -> 0.13969124 | J12: ='Data Sheet'!F21/'Data Sheet'!F$17 -> 0.20349704 | K12: ='Data Sheet'!G21/'Data Sheet'!G$17 -> 0.20308668 | L12: ='Data Sheet'!H21/'Data Sheet'!H$17 -> 0.15801398 | M12: ='Data Sheet'!I21/'Data Sheet'!I$17 -> 0.16979989 | ... O12: ='Data Sheet'!K21/'Data Sheet'!K$17 -> 0
B13: ='Data Sheet'!A22 -> Employee Cost | F13: ='Data Sheet'!B22/'Data Sheet'!B$17 -> 0.03057334 | G13: ='Data Sheet'!C22/'Data Sheet'!C$17 -> 0.025621064 | H13: ='Data Sheet'!D22/'Data Sheet'!D$17 -> 0.029366306 | I13: ='Data Sheet'!E22/'Data Sheet'!E$17 -> 0.038717508 | J13: ='Data Sheet'!F22/'Data Sheet'!F$17 -> 0.031388169 | K13: ='Data Sheet'!G22/'Data Sheet'!G$17 -> 0.023864017 | L13: ='Data Sheet'!H22/'Data Sheet'!H$17 -> 0.023590022 | M13: ='Data Sheet'!I22/'Data Sheet'!I$17 -> 0.026233386 | ... O13: ='Data Sheet'!K22/'Data Sheet'!K$17 -> 0.028495174
B14: ='Data Sheet'!A23 -> Selling and admin | F14: ='Data Sheet'!B23/'Data Sheet'!B$17 -> 0.0058089346 | G14: ='Data Sheet'!C23/'Data Sheet'!C$17 -> 0.0038508056 | H14: ='Data Sheet'!D23/'Data Sheet'!D$17 -> 0.0071026582 | I14: ='Data Sheet'!E23/'Data Sheet'!E$17 -> 0.0061369773 | J14: ='Data Sheet'!F23/'Data Sheet'!F$17 -> 0.0050601836 | K14: ='Data Sheet'!G23/'Data Sheet'!G$17 -> 0.0038053986 | L14: ='Data Sheet'!H23/'Data Sheet'!H$17 -> 0.0061340082 | M14: ='Data Sheet'!I23/'Data Sheet'!I$17 -> 0.0051083963 | ... O14: ='Data Sheet'!K23/'Data Sheet'!K$17 -> 0
B15: ='Data Sheet'!A24 -> Other Expenses | F15: ='Data Sheet'!B24/'Data Sheet'!B$17 -> 0.022300554 | G15: ='Data Sheet'!C24/'Data Sheet'!C$17 -> 0.020324469 | H15: ='Data Sheet'!D24/'Data Sheet'!D$17 -> 0.027360572 | I15: ='Data Sheet'!E24/'Data Sheet'!E$17 -> 0.04062679 | J15: ='Data Sheet'!F24/'Data Sheet'!F$17 -> 0.025188191 | K15: ='Data Sheet'!G24/'Data Sheet'!G$17 -> 0.019962971 | L15: ='Data Sheet'!H24/'Data Sheet'!H$17 -> 0.033423717 | M15: ='Data Sheet'!I24/'Data Sheet'!I$17 -> 0.027736192 | ... O15: ='Data Sheet'!K24/'Data Sheet'!K$17 -> 0.20540249
B16: ='Data Sheet'!A25 -> Other Income | F16: ='Data Sheet'!B25/'Data Sheet'!B$17 -> 0.00032371772 | G16: ='Data Sheet'!C25/'Data Sheet'!C$17 -> -0.0024606231 | H16: ='Data Sheet'!D25/'Data Sheet'!D$17 -> 0.0023124934 | I16: ='Data Sheet'!E25/'Data Sheet'!E$17 -> -0.0039413032 | J16: ='Data Sheet'!F25/'Data Sheet'!F$17 -> 0.0059244229 | K16: ='Data Sheet'!G25/'Data Sheet'!G$17 -> 0.010931127 | L16: ='Data Sheet'!H25/'Data Sheet'!H$17 -> 0.0094058809 | M16: ='Data Sheet'!I25/'Data Sheet'!I$17 -> 0.0085711347 | ... O16: ='Data Sheet'!K25/'Data Sheet'!K$17 -> 0.1003235
B17: ='Data Sheet'!A26 -> Depreciation | F17: ='Data Sheet'!B26/'Data Sheet'!B$17 -> 0.06168621 | G17: ='Data Sheet'!C26/'Data Sheet'!C$17 -> 0.047085482 | H17: ='Data Sheet'!D26/'Data Sheet'!D$17 -> 0.047677478 | I17: ='Data Sheet'!E26/'Data Sheet'!E$17 -> 0.057905791 | J17: ='Data Sheet'!F26/'Data Sheet'!F$17 -> 0.058605443 | K17: ='Data Sheet'!G26/'Data Sheet'!G$17 -> 0.040998558 | L17: ='Data Sheet'!H26/'Data Sheet'!H$17 -> 0.045034948 | M17: ='Data Sheet'!I26/'Data Sheet'!I$17 -> 0.046695542 | ... O17: ='Data Sheet'!K26/'Data Sheet'!K$17 -> 0.051765784
B18: ='Data Sheet'!A27 -> Interest | F18: ='Data Sheet'!B27/'Data Sheet'!B$17 -> 0.067764909 | G18: ='Data Sheet'!C27/'Data Sheet'!C$17 -> 0.051450655 | H18: ='Data Sheet'!D27/'Data Sheet'!D$17 -> 0.046214472 | I18: ='Data Sheet'!E27/'Data Sheet'!E$17 -> 0.058164907 | J18: ='Data Sheet'!F27/'Data Sheet'!F$17 -> 0.049562244 | K18: ='Data Sheet'!G27/'Data Sheet'!G$17 -> 0.03394115 | L18: ='Data Sheet'!H27/'Data Sheet'!H$17 -> 0.041588335 | M18: ='Data Sheet'!I27/'Data Sheet'!I$17 -> 0.046312698 | ... O18: ='Data Sheet'!K27/'Data Sheet'!K$17 -> 0.049075322
B19: ='Data Sheet'!A28 -> Profit before tax | F19: ='Data Sheet'!B28/'Data Sheet'!B$17 -> 0.092223581 | G19: ='Data Sheet'!C28/'Data Sheet'!C$17 -> 0.10636287 | H19: ='Data Sheet'!D28/'Data Sheet'!D$17 -> 0.13176493 | I19: ='Data Sheet'!E28/'Data Sheet'!E$17 -> 0.041090473 | J19: ='Data Sheet'!F28/'Data Sheet'!F$17 -> 0.15049036 | K19: ='Data Sheet'!G28/'Data Sheet'!G$17 -> 0.20321648 | L19: ='Data Sheet'!H28/'Data Sheet'!H$17 -> 0.034074476 | M19: ='Data Sheet'!I28/'Data Sheet'!I$17 -> 0.076454522 | ... O19: ='Data Sheet'!K28/'Data Sheet'!K$17 -> 0.15770745
B20: ='Data Sheet'!A29 -> Tax | F20: ='Data Sheet'!B29/'Data Sheet'!B28 -> 0.32644306 | G20: ='Data Sheet'!C29/'Data Sheet'!C28 -> 0.20101947 | H20: ='Data Sheet'!D29/'Data Sheet'!D28 -> 0.3262894 | I20: ='Data Sheet'!E29/'Data Sheet'!E28 -> -0.30069698 | J20: ='Data Sheet'!F29/'Data Sheet'!F28 -> 0.34473575 | K20: ='Data Sheet'!G29/'Data Sheet'!G28 -> 0.29608338 | L20: ='Data Sheet'!H29/'Data Sheet'!H28 -> 0.26808134 | M20: ='Data Sheet'!I29/'Data Sheet'!I28 -> 0.3293722 | ... O20: ='Data Sheet'!K29/'Data Sheet'!K28 -> 0.12793162
B21: ='Data Sheet'!A30 -> Net profit | F21: ='Data Sheet'!B30/'Data Sheet'!B$17 -> 0.063358751 | G21: ='Data Sheet'!C30/'Data Sheet'!C$17 -> 0.086385942 | H21: ='Data Sheet'!D30/'Data Sheet'!D$17 -> 0.090128249 | I21: ='Data Sheet'!E30/'Data Sheet'!E$17 -> 0.054960041 | J21: ='Data Sheet'!F30/'Data Sheet'!F$17 -> 0.099086912 | K21: ='Data Sheet'!G30/'Data Sheet'!G$17 -> 0.14118234 | L21: ='Data Sheet'!H30/'Data Sheet'!H$17 -> 0.024969872 | M21: ='Data Sheet'!I30/'Data Sheet'!I$17 -> 0.050352559 | ... O21: ='Data Sheet'!K30/'Data Sheet'!K$17 -> 0.12032135
B23: ='Data Sheet'!A32 -> 0
A25: # | B25: Balance Sheet
B27: ='Data Sheet'!A57 -> Equity Share Capital | F27: ='Data Sheet'!B57/'Data Sheet'!B$66 -> 0.0034202602 | G27: ='Data Sheet'!C57/'Data Sheet'!C$66 -> 0.0032836795 | H27: ='Data Sheet'!D57/'Data Sheet'!D$66 -> 0.0026220197 | I27: ='Data Sheet'!E57/'Data Sheet'!E$66 -> 0.0022834168 | J27: ='Data Sheet'!F57/'Data Sheet'!F$66 -> 0.0020521463 | K27: ='Data Sheet'!G57/'Data Sheet'!G$66 -> 0.0015319236 | L27: ='Data Sheet'!H57/'Data Sheet'!H$66 -> 0.0014296639 | M27: ='Data Sheet'!I57/'Data Sheet'!I$66 -> 0.001338318 | ... O27: ='Data Sheet'!K57/'Data Sheet'!K$66 -> 0.0011309868
B28: ='Data Sheet'!A58 -> Reserves | F28: ='Data Sheet'!B58/'Data Sheet'!B$66 -> 0.25391739 | G28: ='Data Sheet'!C58/'Data Sheet'!C$66 -> 0.30114168 | H28: ='Data Sheet'!D58/'Data Sheet'!D$66 -> 0.30047824 | I28: ='Data Sheet'!E58/'Data Sheet'!E$66 -> 0.27536034 | J28: ='Data Sheet'!F58/'Data Sheet'!F$66 -> 0.3078763 | K28: ='Data Sheet'!G58/'Data Sheet'!G$66 -> 0.34097259 | L28: ='Data Sheet'!H58/'Data Sheet'!H$66 -> 0.31060279 | M28: ='Data Sheet'!I58/'Data Sheet'!I$66 -> 0.33946766 | ... O28: ='Data Sheet'!K58/'Data Sheet'!K$66 -> 0.36988089
B29: ='Data Sheet'!A59 -> Borrowings | F29: ='Data Sheet'!B59/'Data Sheet'!B$66 -> 0.49240384 | G29: ='Data Sheet'!C59/'Data Sheet'!C$66 -> 0.42832445 | H29: ='Data Sheet'!D59/'Data Sheet'!D$66 -> 0.41286793 | I29: ='Data Sheet'!E59/'Data Sheet'!E$66 -> 0.46596116 | J29: ='Data Sheet'!F59/'Data Sheet'!F$66 -> 0.4534224 | K29: ='Data Sheet'!G59/'Data Sheet'!G$66 -> 0.36764639 | L29: ='Data Sheet'!H59/'Data Sheet'!H$66 -> 0.38402861 | M29: ='Data Sheet'!I59/'Data Sheet'!I$66 -> 0.38606745 | ... O29: ='Data Sheet'!K59/'Data Sheet'!K$66 -> 0.36825672
B30: ='Data Sheet'!A60 -> Other Liabilities | F30: ='Data Sheet'!B60/'Data Sheet'!B$66 -> 0.25025851 | G30: ='Data Sheet'!C60/'Data Sheet'!C$66 -> 0.26725019 | H30: ='Data Sheet'!D60/'Data Sheet'!D$66 -> 0.28403181 | I30: ='Data Sheet'!E60/'Data Sheet'!E$66 -> 0.25639508 | J30: ='Data Sheet'!F60/'Data Sheet'!F$66 -> 0.23664916 | K30: ='Data Sheet'!G60/'Data Sheet'!G$66 -> 0.2898491 | L30: ='Data Sheet'!H60/'Data Sheet'!H$66 -> 0.30393894 | M30: ='Data Sheet'!I60/'Data Sheet'!I$66 -> 0.27312657 | ... O30: ='Data Sheet'!K60/'Data Sheet'!K$66 -> 0.2607314
B31: Total Liability | F31: ='Data Sheet'!B61/'Data Sheet'!B$66 -> 1 | G31: ='Data Sheet'!C61/'Data Sheet'!C$66 -> 1 | H31: ='Data Sheet'!D61/'Data Sheet'!D$66 -> 1 | I31: ='Data Sheet'!E61/'Data Sheet'!E$66 -> 1 | J31: ='Data Sheet'!F61/'Data Sheet'!F$66 -> 1 | K31: ='Data Sheet'!G61/'Data Sheet'!G$66 -> 1 | L31: ='Data Sheet'!H61/'Data Sheet'!H$66 -> 1 | M31: ='Data Sheet'!I61/'Data Sheet'!I$66 -> 1 | ... O31: ='Data Sheet'!K61/'Data Sheet'!K$66 -> 1
B32: ='Data Sheet'!A62 -> Net Block | F32: ='Data Sheet'!B62/'Data Sheet'!B$66 -> 0.66734845 | G32: ='Data Sheet'!C62/'Data Sheet'!C$66 -> 0.62898771 | H32: ='Data Sheet'!D62/'Data Sheet'!D$66 -> 0.5456937 | I32: ='Data Sheet'!E62/'Data Sheet'!E$66 -> 0.47098316 | J32: ='Data Sheet'!F62/'Data Sheet'!F$66 -> 0.44112311 | K32: ='Data Sheet'!G62/'Data Sheet'!G$66 -> 0.50833397 | L32: ='Data Sheet'!H62/'Data Sheet'!H$66 -> 0.49611711 | M32: ='Data Sheet'!I62/'Data Sheet'!I$66 -> 0.49347076 | ... O32: ='Data Sheet'!K62/'Data Sheet'!K$66 -> 0.43590086
B33: ='Data Sheet'!A63 -> Capital Work in Progress | F33: ='Data Sheet'!B63/'Data Sheet'!B$66 -> 0.049576729 | G33: ='Data Sheet'!C63/'Data Sheet'!C$66 -> 0.064695009 | H33: ='Data Sheet'!D63/'Data Sheet'!D$66 -> 0.10356542 | I33: ='Data Sheet'!E63/'Data Sheet'!E$66 -> 0.20627371 | J33: ='Data Sheet'!F63/'Data Sheet'!F$66 -> 0.22129204 | K33: ='Data Sheet'!G63/'Data Sheet'!G$66 -> 0.086037102 | L33: ='Data Sheet'!H63/'Data Sheet'!H$66 -> 0.10528216 | M33: ='Data Sheet'!I63/'Data Sheet'!I$66 -> 0.13021615 | ... O33: ='Data Sheet'!K63/'Data Sheet'!K$66 -> 0.081178896
B34: ='Data Sheet'!A64 -> Investments | F34: ='Data Sheet'!B64/'Data Sheet'!B$66 -> 0.015521845 | G34: ='Data Sheet'!C64/'Data Sheet'!C$66 -> 0.0159726 | H34: ='Data Sheet'!D64/'Data Sheet'!D$66 -> 0.016498689 | I34: ='Data Sheet'!E64/'Data Sheet'!E$66 -> 0.0095509027 | J34: ='Data Sheet'!F64/'Data Sheet'!F$66 -> 0.050467849 | K34: ='Data Sheet'!G64/'Data Sheet'!G$66 -> 0.025141868 | L34: ='Data Sheet'!H64/'Data Sheet'!H$66 -> 0.022827125 | M34: ='Data Sheet'!I64/'Data Sheet'!I$66 -> 0.031794926 | ... O34: ='Data Sheet'!K64/'Data Sheet'!K$66 -> 0.037889912
B35: ='Data Sheet'!A65 -> Other Assets | F35: ='Data Sheet'!B65/'Data Sheet'!B$66 -> 0.26755298 | G35: ='Data Sheet'!C65/'Data Sheet'!C$66 -> 0.29034468 | H35: ='Data Sheet'!D65/'Data Sheet'!D$66 -> 0.33424218 | I35: ='Data Sheet'!E65/'Data Sheet'!E$66 -> 0.31319223 | J35: ='Data Sheet'!F65/'Data Sheet'!F$66 -> 0.28711701 | K35: ='Data Sheet'!G65/'Data Sheet'!G$66 -> 0.38048706 | L35: ='Data Sheet'!H65/'Data Sheet'!H$66 -> 0.37577361 | M35: ='Data Sheet'!I65/'Data Sheet'!I$66 -> 0.34451816 | ... O35: ='Data Sheet'!K65/'Data Sheet'!K$66 -> 0.44503033
B36: Total Asset | F36: ='Data Sheet'!B66/'Data Sheet'!B$66 -> 1 | G36: ='Data Sheet'!C66/'Data Sheet'!C$66 -> 1 | H36: ='Data Sheet'!D66/'Data Sheet'!D$66 -> 1 | I36: ='Data Sheet'!E66/'Data Sheet'!E$66 -> 1 | J36: ='Data Sheet'!F66/'Data Sheet'!F$66 -> 1 | K36: ='Data Sheet'!G66/'Data Sheet'!G$66 -> 1 | L36: ='Data Sheet'!H66/'Data Sheet'!H$66 -> 1 | M36: ='Data Sheet'!I66/'Data Sheet'!I$66 -> 1 | ... O36: ='Data Sheet'!K66/'Data Sheet'!K$66 -> 1
B37: ='Data Sheet'!A67 -> Receivables | F37: ='Data Sheet'!B67/'Data Sheet'!B$66 -> 0.047145049 | G37: ='Data Sheet'!C67/'Data Sheet'!C$66 -> 0.051147113 | H37: ='Data Sheet'!D67/'Data Sheet'!D$66 -> 0.062370968 | I37: ='Data Sheet'!E67/'Data Sheet'!E$66 -> 0.034175391 | J37: ='Data Sheet'!F67/'Data Sheet'!F$66 -> 0.030483206 | K37: ='Data Sheet'!G67/'Data Sheet'!G$66 -> 0.037952007 | L37: ='Data Sheet'!H67/'Data Sheet'!H$66 -> 0.033884458 | M37: ='Data Sheet'!I67/'Data Sheet'!I$66 -> 0.03312008 | ... O37: ='Data Sheet'!K67/'Data Sheet'!K$66 -> 0.041753808
B38: ='Data Sheet'!A68 -> Inventory | F38: ='Data Sheet'!B68/'Data Sheet'!B$66 -> 0.12948128 | G38: ='Data Sheet'!C68/'Data Sheet'!C$66 -> 0.13693596 | H38: ='Data Sheet'!D68/'Data Sheet'!D$66 -> 0.12672805 | I38: ='Data Sheet'!E68/'Data Sheet'!E$66 -> 0.10448339 | J38: ='Data Sheet'!F68/'Data Sheet'!F$66 -> 0.096824609 | K38: ='Data Sheet'!G68/'Data Sheet'!G$66 -> 0.17195715 | L38: ='Data Sheet'!H68/'Data Sheet'!H$66 -> 0.15738177 | M38: ='Data Sheet'!I68/'Data Sheet'!I$66 -> 0.16592949 | ... O38: ='Data Sheet'!K68/'Data Sheet'!K$66 -> 0.12149765
B39: ='Data Sheet'!A69 -> Cash & Bank | F39: ='Data Sheet'!B69/'Data Sheet'!B$66 -> 0.016874041 | G39: ='Data Sheet'!C69/'Data Sheet'!C$66 -> 0.011558117 | H39: ='Data Sheet'!D69/'Data Sheet'!D$66 -> 0.053895137 | I39: ='Data Sheet'!E69/'Data Sheet'!E$66 -> 0.091055985 | J39: ='Data Sheet'!F69/'Data Sheet'!F$66 -> 0.087066722 | K39: ='Data Sheet'!G69/'Data Sheet'!G$66 -> 0.088469858 | L39: ='Data Sheet'!H69/'Data Sheet'!H$66 -> 0.098385572 | M39: ='Data Sheet'!I69/'Data Sheet'!I$66 -> 0.054182134 | ... O39: ='Data Sheet'!K69/'Data Sheet'!K$66 -> 0.1519935

Sheet Ratio Analysis
B2: Ratio Analysis
B5: Particulars | C5: ='Data Sheet'!B16 -> 42825 | D5: ='Data Sheet'!C16 -> 43190 | E5: ='Data Sheet'!D16 -> 43555 | F5: ='Data Sheet'!E16 -> 43921 | G5: ='Data Sheet'!F16 -> 44286 | H5: ='Data Sheet'!G16 -> 44651 | I5: ='Data Sheet'!H16 -> 45016 | J5: ='Data Sheet'!I16 -> 45382 | ... L5: ='Data Sheet'!K16 -> 46112 | M5: LTM | N5: line chart | O5: mean | P5: median
B7: SalesGrowth | D7: =IFERROR(Historical!D7/Historical!C7-1,0) -> 0.29366592 | E7: =IFERROR(Historical!E7/Historical!D7-1,0) -> 0.17827701 | F7: =IFERROR(Historical!F7/Historical!E7-1,0) -> -0.13486792 | G7: =IFERROR(Historical!G7/Historical!F7-1,0) -> 0.088822519 | H7: =IFERROR(Historical!H7/Historical!G7-1,0) -> 0.83332707 | I7: =IFERROR(Historical!I7/Historical!H7-1,0) -> 0.13383116 | J7: =IFERROR(Historical!J7/Historical!I7-1,0) -> 0.05450711 | K7: =IFERROR(Historical!K7/Historical!J7-1,0) -> -0.035324503 | L7: =IFERROR(Historical!L7/Historical!K7-1,0) -> 0.098599725 | O7: =AVERAGE(D7:L7) -> 0.1678709 | P7: =MEDIAN(C7:L7) -> 0.098599725
B8: EBITDA Growth | D8: =IFERROR(Historical!D19/Historical!C19-1,0) -> 0.2118947 | E8: =IFERROR(Historical!E19/Historical!D19-1,0) -> 0.269107 | F8: =IFERROR(Historical!F19/Historical!E19-1,0) -> -0.37596408 | G8: =IFERROR(Historical!G19/Historical!F19-1,0) -> 0.70811817 | H8: =IFERROR(Historical!H19/Historical!G19-1,0) -> 0.93844781 | I8: =IFERROR(Historical!I19/Historical!H19-1,0) -> -0.52779056 | J8: =IFERROR(Historical!J19/Historical!I19-1,0) -> 0.52447212 | K8: =IFERROR(Historical!K19/Historical!J19-1,0) -> -0.19291828 | L8: =IFERROR(Historical!L19/Historical!K19-1,0) -> 0.29135314 | O8: =AVERAGE(D8:L8) -> 0.20519111 | P8: =MEDIAN(C8:L8) -> 0.269107
B9: EBIT Growth | D9: =IFERROR((Historical!D19-Historical!D25)/(Historical!C19-Historical!C25),0) -> 1.2986033 | E9: =IFERROR((Historical!E19-Historical!E25)/(Historical!D19-Historical!D25),0) -> 1.291439 | F9: =IFERROR((Historical!F19-Historical!F25)/(Historical!E19-Historical!E25),0) -> 0.50822755 | G9: =IFERROR((Historical!G19-Historical!G25)/(Historical!F19-Historical!F25),0) -> 2.0482358 | H9: =IFERROR((Historical!H19-Historical!H25)/(Historical!G19-Historical!G25),0) -> 2.1364604 | I9: =IFERROR((Historical!I19-Historical!I25)/(Historical!H19-Historical!H25),0) -> 0.33207502 | J9: =IFERROR((Historical!J19-Historical!J25)/(Historical!I19-Historical!I25),0) -> 1.8174791 | K9: =IFERROR((Historical!K19-Historical!K25)/(Historical!J19-Historical!J25),0) -> 0.67130348 | L9: =IFERROR((Historical!L19-Historical!L25)/(Historical!K19-Historical!K25),0) -> 1.4717501 | O9: =AVERAGE(D9:L9) -> 1.2861749 | P9: =MEDIAN(C9:L9) -> 1.2986033
B10: Net Profit Growth | D10: =IFERROR(Historical!D34/Historical!C34-1,0) -> 0.830617 | E10: =IFERROR(Historical!E34/Historical!D34-1,0) -> 0.16502385 | F10: =IFERROR(Historical!F34/Historical!E34-1,0) -> -0.42576419 | G10: =IFERROR(Historical!G34/Historical!F34-1,0) -> 0.75855513 | H10: =IFERROR(Historical!H34/Historical!G34-1,0) -> 1.6132432 | I10: =IFERROR(Historical!I34/Historical!H34-1,0) -> -0.86668735 | J10: =IFERROR(Historical!J34/Historical!I34-1,0) -> 1.8987587 | K10: =IFERROR(Historical!K34/Historical!J34-1,0) -> -0.5426201 | L10: =IFERROR(Historical!L34/Historical!K34-1,0) -> 1.019017 | O10: =AVERAGE(D10:L10) -> 0.49446036 | P10: =MEDIAN(C10:L10) -> 0.75855513
B11: Dividend Growth | D11: =IFERROR(Historical!D22/Historical!C22-1,0) -> -0.017781316 | E11: =IFERROR(Historical!E22/Historical!D22-1,0) -> 0.058362605 | F11: =IFERROR(Historical!F22/Historical!E22-1,0) -> 0.088843503 | G11: =IFERROR(Historical!G22/Historical!F22-1,0) -> -0.072215709 | H11: =IFERROR(Historical!H22/Historical!G22-1,0) -> 0.25549659 | I11: =IFERROR(Historical!I22/Historical!H22-1,0) -> 0.38929147 | J11: =IFERROR(Historical!J22/Historical!I22-1,0) -> 0.17429731 | K11: =IFERROR(Historical!K22/Historical!J22-1,0) -> 0.037877853 | L11: =IFERROR(Historical!L22/Historical!K22-1,0) -> 0.082025678 | O11: =AVERAGE(D11:L11) -> 0.11068866 | P11: =MEDIAN(C11:L11) -> 0.082025678
B14: Gross Margin | C14: =IFERROR(Historical!C14,0) -> 0.24946047 | D14: =IFERROR(Historical!D14,0) -> 0.2315349 | E14: =IFERROR(Historical!E14,0) -> 0.25780761 | F14: =IFERROR(Historical!F14,0) -> 0.20786624 | G14: =IFERROR(Historical!G14,0) -> 0.282982 | H14: =IFERROR(Historical!H14,0) -> 0.29099343 | I14: =IFERROR(Historical!I14,0) -> 0.1508496 | J14: =IFERROR(Historical!J14,0) -> 0.19373621 | ... L14: =IFERROR(Historical!L14,0) -> 0.36362754 | O14: =AVERAGE(C14:L14) -> 0.24001429 | P14: =MEDIAN(C14:L14) -> 0.24049769
B15: Operating Margin | C15: =IFERROR((Historical!C19-Historical!C25)/Historical!C7,0) -> 0.15966477 | D15: =IFERROR((Historical!D19-Historical!D25)/Historical!D7,0) -> 0.16027414 | E15: =IFERROR((Historical!E19-Historical!E25)/Historical!E7,0) -> 0.17566691 | F15: =IFERROR((Historical!F19-Historical!F25)/Historical!F7,0) -> 0.10319668 | G15: =IFERROR((Historical!G19-Historical!G25)/Historical!G7,0) -> 0.19412818 | H15: =IFERROR((Historical!H19-Historical!H25)/Historical!H7,0) -> 0.22622651 | I15: =IFERROR((Historical!I19-Historical!I25)/Historical!I7,0) -> 0.066256929 | J15: =IFERROR((Historical!J19-Historical!J25)/Historical!J7,0) -> 0.11419608 | ... L15: =IFERROR((Historical!L19-Historical!L25)/Historical!L7,0) -> 0.10645927 | O15: =AVERAGE(C15:L15) -> 0.13855368 | P15: =MEDIAN(C15:L15) -> 0.13693043
B16: EBITDA Margin | C16: =IFERROR(Historical!C20,0) -> 0.22135098 | D16: =IFERROR(Historical!D20,0) -> 0.20735963 | E16: =IFERROR(Historical!E20,0) -> 0.22334438 | F16: =IFERROR(Historical!F20,0) -> 0.16110247 | G16: =IFERROR(Historical!G20,0) -> 0.25273363 | H16: =IFERROR(Historical!H20,0) -> 0.26722507 | I16: =IFERROR(Historical!I20,0) -> 0.11129188 | J16: =IFERROR(Historical!J20,0) -> 0.16089163 | ... L16: =IFERROR(Historical!L20,0) -> 0.15822505 | O16: =AVERAGE(C16:L16) -> 0.18981324 | P16: =MEDIAN(C16:L16) -> 0.18423105
B17: EBT Margin | C17: =IFERROR(Historical!C29,0) -> 0.091899863 | D17: =IFERROR(Historical!D29,0) -> 0.10882349 | E17: =IFERROR(Historical!E29,0) -> 0.12945243 | F17: =IFERROR(Historical!F29,0) -> 0.045031776 | G17: =IFERROR(Historical!G29,0) -> 0.14456594 | H17: =IFERROR(Historical!H29,0) -> 0.19228536 | I17: =IFERROR(Historical!I29,0) -> 0.024668595 | J17: =IFERROR(Historical!J29,0) -> 0.067883387 | ... L17: =IFERROR(Historical!L29,0) -> 0.057383943 | O17: =AVERAGE(C17:L17) -> 0.089163512 | P17: =MEDIAN(C17:L17) -> 0.079891625
B18: Net Profit Margin | C18: =IFERROR(Historical!C35,0) -> 0.061794116 | D18: =IFERROR(Historical!D35,0) -> 0.087442481 | E18: =IFERROR(Historical!E35,0) -> 0.086458936 | F18: =IFERROR(Historical!F35,0) -> 0.057387557 | G18: =IFERROR(Historical!G35,0) -> 0.092686532 | H18: =IFERROR(Historical!H35,0) -> 0.13211633 | I18: =IFERROR(Historical!I35,0) -> 0.015533864 | J18: =IFERROR(Historical!J35,0) -> 0.042701393 | ... L18: =IFERROR(Historical!L35,0) -> 0.037208174 | O18: =AVERAGE(C18:L18) -> 0.063357532 | P18: =MEDIAN(C18:L18) -> 0.059590836
B21: SalesExpenses%Sales | C21: =IFERROR(Historical!C17,0) -> 0.028109489 | D21: =IFERROR(Historical!D17,0) -> 0.024175274 | E21: =IFERROR(Historical!E17,0) -> 0.03446323 | F21: =IFERROR(Historical!F17,0) -> 0.046763767 | G21: =IFERROR(Historical!G17,0) -> 0.030248375 | H21: =IFERROR(Historical!H17,0) -> 0.023768369 | I21: =IFERROR(Historical!I17,0) -> 0.039557725 | J21: =IFERROR(Historical!J17,0) -> 0.032844588 | ... L21: =IFERROR(Historical!L17,0) -> 0.20540249 | O21: =AVERAGE(C21:L21) -> 0.050201056 | P21: =MEDIAN(C21:L21) -> 0.033653909
B22: Depreciation%Sales | C22: =IFERROR(Historical!C26,0) -> 0.06168621 | D22: =IFERROR(Historical!D26,0) -> 0.047085482 | E22: =IFERROR(Historical!E26,0) -> 0.047677478 | F22: =IFERROR(Historical!F26,0) -> 0.057905791 | G22: =IFERROR(Historical!G26,0) -> 0.058605443 | H22: =IFERROR(Historical!H26,0) -> 0.040998558 | I22: =IFERROR(Historical!I26,0) -> 0.045034948 | J22: =IFERROR(Historical!J26,0) -> 0.046695542 | ... L22: =IFERROR(Historical!L26,0) -> 0.051765784 | O22: =AVERAGE(C22:L22) -> 0.05125955 | P22: =MEDIAN(C22:L22) -> 0.049721631
B23: OperatingIncome%Sales | C23: =C15 -> 0.15966477 | D23: =D15 -> 0.16027414 | E23: =E15 -> 0.17566691 | F23: =F15 -> 0.10319668 | G23: =G15 -> 0.19412818 | H23: =H15 -> 0.22622651 | I23: =I15 -> 0.066256929 | J23: =J15 -> 0.11419608 | ... L23: =L15 -> 0.10645927 | O23: =AVERAGE(C23:L23) -> 0.13855368 | P23: =MEDIAN(C23:L23) -> 0.13693043
B25: Return on Capital Employed | C25: =IFERROR((Historical!C19-Historical!C25)/SUM(Historical!C52,Historical!C53,Historical!C54),0) -> 0.13455389 | D25: =IFERROR((Historical!D19-Historical!D25)/SUM(Historical!D52,Historical!D53,Historical!D54),0) -> 0.17107626 | E25: =IFERROR((Historical!E19-Historical!E25)/SUM(Historical!E52,Historical!E53,Historical!E54),0) -> 0.18115122 | F25: =IFERROR((Historical!F19-Historical!F25)/SUM(Historical!F52,Historical!F53,Historical!F54),0) -> 0.077196956 | G25: =IFERROR((Historical!G19-Historical!G25)/SUM(Historical!G52,Historical!G53,Historical!G54),0) -> 0.13796879 | H25: =IFERROR((Historical!H19-Historical!H25)/SUM(Historical!H52,Historical!H53,Historical!H54),0) -> 0.23731134 | I25: =IFERROR((Historical!I19-Historical!I25)/SUM(Historical!I52,Historical!I53,Historical!I54),0) -> 0.075033436 | J25: =IFERROR((Historical!J19-Historical!J25)/SUM(Historical!J52,Historical!J53,Historical!J54),0) -> 0.12064376 | ... L25: =IFERROR((Historical!L19-Historical!L25)/SUM(Historical!L52,Historical!L53,Historical!L54),0) -> 0.099040444 | O25: =AVERAGE(C25:L25) -> 0.1309242 | P25: =MEDIAN(C25:L25) -> 0.12759882
B26: Retained Earnings% | C26: =IFERROR(Historical!C45,0) -> 0.80289581 | D26: =IFERROR(Historical!D45,0) -> 0.8463593 | E26: =IFERROR(Historical!E45,0) -> 0.83159116 | F26: =IFERROR(Historical!F45,0) -> 0.85693916 | G26: =IFERROR(Historical!G45,0) -> 0.73472973 | H26: =IFERROR(Historical!H45,0) -> 0.72994363 | I26: =IFERROR(Historical!I45,0) -> 0.6030256 | J26: =IFERROR(Historical!J45,0) -> 0.70206075 | ... L26: =IFERROR(Historical!L45,0) -> 0.6862049 | O26: =AVERAGE(C26:L26) -> 0.75438963 | P26: =MEDIAN(C26:L26) -> 0.74243801
B27: Return on Equity% | C27: =IFERROR(Historical!C34/SUM(Historical!C52:C53),0) -> 0.15171987 | D27: =IFERROR(Historical!D34/SUM(Historical!D52:D53),0) -> 0.2246589 | E27: =IFERROR(Historical!E34/SUM(Historical!E52:E53),0) -> 0.21060497 | F27: =IFERROR(Historical!F34/SUM(Historical!F52:F53),0) -> 0.11497582 | G27: =IFERROR(Historical!G34/SUM(Historical!G52:G53),0) -> 0.16224512 | H27: =IFERROR(Historical!H34/SUM(Historical!H52:H53),0) -> 0.28735308 | I27: =IFERROR(Historical!I34/SUM(Historical!I52:I53),0) -> 0.039241951 | J27: =IFERROR(Historical!J34/SUM(Historical!J52:J53),0) -> 0.096215994 | ... L27: =IFERROR(Historical!L34/SUM(Historical!L52:L53),0) -> 0.068973444 | O27: =AVERAGE(C27:L27) -> 0.1398985 | P27: =MEDIAN(C27:L27) -> 0.13334785
B28: Self Sustained Growth Rate | C28: =IFERROR(C27*C26,0) -> 0.12181525 | D28: =IFERROR(D27*D26,0) -> 0.19014215 | E28: =IFERROR(E27*E26,0) -> 0.17513723 | F28: =IFERROR(F27*F26,0) -> 0.098527282 | G28: =IFERROR(G27*G26,0) -> 0.11920631 | H28: =IFERROR(H27*H26,0) -> 0.20975155 | I28: =IFERROR(I27*I26,0) -> 0.023663901 | J28: =IFERROR(J27*J26,0) -> 0.067549473 | ... L28: =IFERROR(L27*L26,0) -> 0.047329915 | O28: =AVERAGE(C28:L28) -> 0.10853763 | P28: =MEDIAN(C28:L28) -> 0.1088668
B29: Interest Coverage Ratio | C29: =IFERROR((Historical!C19-Historical!C25)/Historical!C22,0) -> 2.3561571 | D29: =IFERROR((Historical!D19-Historical!D25)/Historical!D22,0) -> 3.115104 | E29: =IFERROR((Historical!E19-Historical!E25)/Historical!E22,0) -> 3.8011233 | F29: =IFERROR((Historical!F19-Historical!F25)/Historical!F22,0) -> 1.7742087 | G29: =IFERROR((Historical!G19-Historical!G25)/Historical!G22,0) -> 3.9168562 | H29: =IFERROR((Historical!H19-Historical!H25)/Historical!H22,0) -> 6.6652576 | I29: =IFERROR((Historical!I19-Historical!I25)/Historical!I22,0) -> 1.5931614 | J29: =IFERROR((Historical!J19-Historical!J25)/Historical!J22,0) -> 2.4657619 | ... L29: =IFERROR((Historical!L19-Historical!L25)/Historical!L22,0) -> 2.1693034 | O29: =AVERAGE(C29:L29) -> 2.9451798 | P29: =MEDIAN(C29:L29) -> 2.4109595
B31: Debtor Turnover Ratio | D31: =IFERROR(Historical!D7/AVERAGE(Historical!D64:E64),0) -> 12.126264 | E31: =IFERROR(Historical!E7/AVERAGE(Historical!E64:F64),0) -> 14.531847 | F31: =IFERROR(Historical!F7/AVERAGE(Historical!F64:G64),0) -> 16.310978 | G31: =IFERROR(Historical!G7/AVERAGE(Historical!G64:H64),0) -> 13.370008 | H31: =IFERROR(Historical!H7/AVERAGE(Historical!H64:I64),0) -> 20.06319 | I31: =IFERROR(Historical!I7/AVERAGE(Historical!I64:J64),0) -> 22.607274 | J31: =IFERROR(Historical!J7/AVERAGE(Historical!J64:K64),0) -> 21.926455 | K31: =IFERROR(Historical!K7/AVERAGE(Historical!K64:L64),0) -> 17.161271 | L31: =IFERROR(Historical!L7/AVERAGE(Historical!L64:M64),0) -> 16.471581 | O31: =AVERAGE(C31:L31) -> 17.174319 | P31: =MEDIAN(C31:L31) -> 16.471581
B32: Creditor Turnover Ratio | D32: =IFERROR((Historical!D65-Historical!C65+Historical!D10)/AVERAGE(Historical!C55:D55),0) -> 2.4237495 | E32: =IFERROR((Historical!E65-Historical!D65+Historical!E10)/AVERAGE(Historical!D55:E55),0) -> 2.268427 | F32: =IFERROR((Historical!F65-Historical!E65+Historical!F10)/AVERAGE(Historical!E55:F55),0) -> 1.7260707 | G32: =IFERROR((Historical!G65-Historical!F65+Historical!G10)/AVERAGE(Historical!F55:G55),0) -> 1.6822686 | H32: =IFERROR((Historical!H65-Historical!G65+Historical!H10)/AVERAGE(Historical!G55:H55),0) -> 2.6872964 | I32: =IFERROR((Historical!I65-Historical!H65+Historical!I10)/AVERAGE(Historical!H55:I55),0) -> 2.3196739 | J32: =IFERROR((Historical!J65-Historical!I65+Historical!J10)/AVERAGE(Historical!I55:J55),0) -> 2.3096581 | K32: =IFERROR((Historical!K65-Historical!J65+Historical!K10)/AVERAGE(Historical!J55:K55),0) -> 2.2026004 | L32: =IFERROR((Historical!L65-Historical!K65+Historical!L10)/AVERAGE(Historical!K55:L55),0) -> 1.7483511 | O32: =AVERAGE(C32:L32) -> 2.1520106 | P32: =MEDIAN(C32:L32) -> 2.268427
B33: Inventory Turnover | D33: =IFERROR(Historical!D10/AVERAGE(Historical!C65:D65),0) -> 4.6086123 | E33: =IFERROR(Historical!E10/AVERAGE(Historical!D65:E65),0) -> 4.6353253 | F33: =IFERROR(Historical!F10/AVERAGE(Historical!E65:F65),0) -> 4.1018326 | G33: =IFERROR(Historical!G10/AVERAGE(Historical!F65:G65),0) -> 4.0857897 | H33: =IFERROR(Historical!H10/AVERAGE(Historical!G65:H65),0) -> 4.3208427 | I33: =IFERROR(Historical!I10/AVERAGE(Historical!H65:I65),0) -> 4.2116195 | J33: =IFERROR(Historical!J10/AVERAGE(Historical!I65:J65),0) -> 3.9774771 | K33: =IFERROR(Historical!K10/AVERAGE(Historical!J65:K65),0) -> 3.8451306 | L33: =IFERROR(Historical!L10/AVERAGE(Historical!K65:L65),0) -> 3.4857134 | O33: =AVERAGE(C33:L33) -> 4.1413715 | P33: =MEDIAN(C33:L33) -> 4.1018326
B34: Fixed Asset Turnover | D34: =IFERROR(Historical!D7/AVERAGE(Historical!C58:D58),0) -> 1.234075 | E34: =IFERROR(Historical!E7/AVERAGE(Historical!D58:E58),0) -> 1.4068486 | F34: =IFERROR(Historical!F7/AVERAGE(Historical!E58:F58),0) -> 1.1757651 | G34: =IFERROR(Historical!G7/AVERAGE(Historical!F58:G58),0) -> 1.2572873 | H34: =IFERROR(Historical!H7/AVERAGE(Historical!G58:H58),0) -> 1.7763794 | I34: =IFERROR(Historical!I7/AVERAGE(Historical!H58:I58),0) -> 1.6244152 | J34: =IFERROR(Historical!J7/AVERAGE(Historical!I58:J58),0) -> 1.6136055 | K34: =IFERROR(Historical!K7/AVERAGE(Historical!J58:K58),0) -> 1.4251141 | L34: =IFERROR(Historical!L7/AVERAGE(Historical!K58:L58),0) -> 1.5326959 | O34: =AVERAGE(C34:L34) -> 1.4495762 | P34: =MEDIAN(C34:L34) -> 1.4251141
B35: Capital Turnover Ratio | C35: =IFERROR(Historical!C7/SUM(Historical!C52:C54),0) -> 0.84272745 | D35: =IFERROR(Historical!D7/SUM(Historical!D52:D54),0) -> 1.0673977 | E35: =IFERROR(Historical!E7/SUM(Historical!E52:E54),0) -> 1.03122 | F35: =IFERROR(Historical!F7/SUM(Historical!F52:F54),0) -> 0.74805656 | G35: =IFERROR(Historical!G7/SUM(Historical!G52:G54),0) -> 0.71070974 | H35: =IFERROR(Historical!H7/SUM(Historical!H52:H54),0) -> 1.0489988 | I35: =IFERROR(Historical!I7/SUM(Historical!I52:I54),0) -> 1.1324617 | J35: =IFERROR(Historical!J7/SUM(Historical!J52:J54),0) -> 1.0564614 | ... L35: =IFERROR(Historical!L7/SUM(Historical!L52:L54),0) -> 0.93031305 | O35: =AVERAGE(C35:L35) -> 0.95154763 | P35: =MEDIAN(C35:L35) -> 0.9891749
B37: (in days)
B38: Debtor Days | D38: =365/D31 -> 30.099954 | E38: =365/E31 -> 25.117247 | F38: =365/F31 -> 22.377567 | G38: =365/G31 -> 27.29991 | H38: =365/H31 -> 18.192521 | I38: =365/I31 -> 16.145246 | J38: =365/J31 -> 16.646558 | K38: =365/K31 -> 21.268821 | L38: =365/L31 -> 22.159379 | O38: =AVERAGE(D38:L38) -> 22.145245 | P38: =AVERAGE(E38:M38) -> 21.150906
B39: Payable Days | D39: =365/D32 -> 150.59312 | E39: =365/E32 -> 160.90445 | F39: =365/F32 -> 211.46295 | G39: =365/G32 -> 216.96892 | H39: =365/H32 -> 135.82424 | I39: =365/I32 -> 157.3497 | J39: =365/J32 -> 158.03205 | K39: =365/K32 -> 165.71322 | L39: =365/L32 -> 208.76814 | O39: =AVERAGE(D39:L39) -> 173.95742 | P39: =AVERAGE(E39:M39) -> 176.87796
B40: Inventory Days | D40: =365/D33 -> 79.199546 | E40: =365/E33 -> 78.743125 | F40: =365/F33 -> 88.984617 | G40: =365/G33 -> 89.334015 | H40: =365/H33 -> 84.474262 | I40: =365/I33 -> 86.664999 | J40: =365/J33 -> 91.766713 | K40: =365/K33 -> 94.925254 | L40: =365/L33 -> 104.71314 | O40: =AVERAGE(D40:L40) -> 88.756186 | P40: =AVERAGE(E40:M40) -> 89.950766
B41: Cash Conversion Cycle | D41: =D38+D40-D39 -> -41.293617 | E41: =E38+E40-E39 -> -57.044076 | F41: =F38+F40-F39 -> -100.10076 | G41: =G38+G40-G39 -> -100.335 | H41: =H38+H40-H39 -> -33.157461 | I41: =I38+I40-I39 -> -54.539459 | J41: =J38+J40-J39 -> -49.618777 | K41: =K38+K40-K39 -> -49.519142 | L41: =L38+L40-L39 -> -81.895621 | O41: =AVERAGE(D41:L41) -> -63.05599 | P41: =AVERAGE(E41:M41) -> -65.776287
B43: CFO/Sales | C43: =IFERROR(Historical!C75/Historical!C7,0) -> 0.1418603 | D43: =IFERROR(Historical!D75/Historical!D7,0) -> 0.1720907 | E43: =IFERROR(Historical!E75/Historical!E7,0) -> 0.17264651 | F43: =IFERROR(Historical!F75/Historical!F7,0) -> 0.17435834 | G43: =IFERROR(Historical!G75/Historical!G7,0) -> 0.23586217 | H43: =IFERROR(Historical!H75/Historical!H7,0) -> 0.17947544 | I43: =IFERROR(Historical!I75/Historical!I7,0) -> 0.14053386 | J43: =IFERROR(Historical!J75/Historical!J7,0) -> 0.069014777 | ... L43: =IFERROR(Historical!L75/Historical!L7,0) -> 0.13561223 | O43: =AVERAGE(C43:L43) -> 0.1545246 | P43: =MEDIAN(C43:L43) -> 0.1569755
B44: CFO/Total Assets | C44: =IFERROR(Historical!C75/Historical!C69,0) -> 0.089631271 | D44: =IFERROR(Historical!D75/Historical!D69,0) -> 0.13459824 | E44: =IFERROR(Historical!E75/Historical!E69,0) -> 0.12746849 | F44: =IFERROR(Historical!F75/Historical!F69,0) -> 0.096988317 | G44: =IFERROR(Historical!G75/Historical!G69,0) -> 0.12796015 | H44: =IFERROR(Historical!H75/Historical!H69,0) -> 0.13369977 | I44: =IFERROR(Historical!I75/Historical!I69,0) -> 0.11077758 | J44: =IFERROR(Historical!J75/Historical!J69,0) -> 0.052997394 | ... L44: =IFERROR(Historical!L75/Historical!L69,0) -> 0.093267477 | O44: =AVERAGE(C44:L44) -> 0.10543067 | P44: =MEDIAN(C44:L44) -> 0.10388295
B45: CFO/Total Debt | C45: =IFERROR(Historical!C75/Historical!C54,0) -> 0.18202797 | D45: =IFERROR(Historical!D75/Historical!D54,0) -> 0.31424365 | E45: =IFERROR(Historical!E75/Historical!E54,0) -> 0.30873913 | F45: =IFERROR(Historical!F75/Historical!F54,0) -> 0.20814679 | G45: =IFERROR(Historical!G75/Historical!G54,0) -> 0.2822096 | H45: =IFERROR(Historical!H75/Historical!H54,0) -> 0.36366405 | I45: =IFERROR(Historical!I75/Historical!I54,0) -> 0.28846178 | J45: =IFERROR(Historical!J75/Historical!J54,0) -> 0.13727496 | ... L45: =IFERROR(Historical!L75/Historical!L54,0) -> 0.25326755 | O45: =AVERAGE(C45:L45) -> 0.25496666 | P45: =MEDIAN(C45:L45) -> 0.26773857

Sheet DCF Model
B2: Dicounted Cash Flow Model
A5: # | B5: Terminal Value Calculation
B6: ="FCFF "&FCFF!J28&"E" -> FCFF 2032E | E6: =FCFF!J49 -> 15250.407
B7: Terminal growth rate | E7: =FCFF!F20 -> 0.065
B8: WACC | E8: =WACC!L42 -> 0.11111774
B9: Terminal Value | E9: =(E6*(1+E7)/(E8-E7)) -> 352178.67
A12: # | B12: Present Value Calculation
B13: Particulars | E13: =FCFF!E28 -> 2027 | F13: =FCFF!F28 -> 2028 | G13: =FCFF!G28 -> 2029 | H13: =FCFF!H28 -> 2030 | I13: =FCFF!I28 -> 2031 | J13: =FCFF!J28 -> 2032 | K13: ="Terminal Value "&J13 -> Terminal Value 2032
B15: FCFF | E15: =FCFF!E49 -> 11627.965 | F15: =FCFF!F49 -> 12408.018 | G15: =FCFF!G49 -> 13424.834 | H15: =FCFF!H49 -> 14392.857 | I15: =FCFF!I49 -> 14945.144 | J15: =FCFF!J49 -> 15250.407 | L15: =E9 -> 352178.67
B16: Discout Factor | E16: =1/(1+WACC!$L$42)^1 -> 0.89999463 | F16: =1/(1+WACC!$L$42)^2 -> 0.80999034 | G16: =1/(1+WACC!$L$42)^3 -> 0.72898696 | H16: =1/(1+WACC!$L$42)^4 -> 0.65608435 | I16: =1/(1+WACC!$L$42)^5 -> 0.59047239 | J16: =1/(1+WACC!$L$42)^6 -> 0.53142198 | L16: =J16 -> 0.53142198
B17: PV of FCFF | E17: =E15*E16 -> 10465.106 | F17: =F15*F16 -> 10050.375 | G17: =G15*G16 -> 9786.5287 | H17: =H15*H16 -> 9442.9284 | I17: =I15*I16 -> 8824.6948 | J17: =J15*J16 -> 8104.4017 | L17: =L15*L16 -> 187155.49
A20: # | B20: Value of Enterprise | H20: # | I20: Value of Equity
B21: PV of FCFF | E21: =SUBTOTAL(109,E17:J17) -> 56674.035 | I21: Enterprise Value | L21: =SUM(E21:E22) -> 243829.52
B22: PV of terminal Value | E22: =L17 -> 187155.49 | I22: Less: Debt | L22: ='Data Sheet'!K59 -> 99310
B23: Enterprise Value | E23: =SUM(E21:E22) -> 243829.52 | I23: Add: Cash&Investment | L23: ='Data Sheet'!K69 -> 40989
I24: Equity Value | L24: =L21-L22+L23 -> 185508.52
A26: # | B26: Intrensic Value
B27: Value of Equity | E27: =L24 -> 185508.52
B28: No. of share outstanding | E28: ='Data Sheet'!B6 -> 244.5454
B29: value per share | E29: =E27/E28 -> 758.58522
A38: # | B38: Senstivity Analysis
B40: Terminal growth/WACC
B42: =E29 -> 758.58522 | C42: 0.0981 | D42: 0.1006 | E42: 0.1031 | F42: 0.1056 | G42: 0.1081 | H42: 0.1111 | I42: 0.1141 | J42: 0.1171 | K42: 0.1201 | L42: 0.1231 | M42: 0.1261
B43: 0.0525 | C43: 758.18997 | D43: 718.43296 | E43: 682.60452 | F43: 650.14975 | G43: 620.61357 | H43: 588.49676 | I43: 559.50821 | J43: 533.21209 | K43: 509.24995 | L43: 487.32426 | M43: 467.18598
B44: 0.055 | C44: 804.48147 | D44: 760.00689 | E44: 720.15545 | F44: 684.2419 | G44: 651.71004 | H44: 616.49909 | I44: 584.86285 | J44: 556.28325 | K44: 530.33772 | L44: 506.67814 | M44: 485.01514
B45: 0.0575 | C45: 856.47389 | D45: 806.40378 | E45: 761.82381 | F45: 721.87794 | G45: 685.87929 | H45: 647.11357 | I45: 612.4573 | J45: 581.28991 | K45: 553.10981 | L45: 527.50716 | M45: 504.14381
B46: 0.06 | C46: 915.28947 | D46: 858.51457 | E46: 808.32609 | F46: 763.64074 | G46: 723.60043 | H46: 680.72361 | I46: 642.60207 | J46: 608.48629 | K46: 577.77642 | L46: 549.98667 | M46: 524.71943
B47: 0.0625 | C47: 982.36566 | D47: 917.46405 | E47: 860.55526 | F47: 810.24841 | G47: 765.45766 | H47: 717.79146 | I47: 675.66784 | J47: 638.17319 | K47: 604.58423 | L47: 574.32091 | M47: 546.91262
B48: 0.065 | C48: 1059.5742 | D48: 984.69295 | E48: 919.63864 | F48: 862.59594 | G48: 812.17072 | H48: 758.87969 | I48: 712.1008 | J48: 670.70911 | K48: 633.82469 | L48: 600.74933 | M48: 570.92196
B49: 0.0675 | C49: 1149.3985 | D49: 1062.0773 | E49: 987.02025 | F49: 921.81322 | G49: 864.63662 | H49: 804.67987 | I49: 752.44287 | J49: 706.52487 | K49: 665.84466 | L49: 629.5544 | M49: 596.97987
B50: 0.07 | C50: 1255.2058 | D50: 1152.1061 | E50: 1064.5803 | F50: 989.34754 | G50: 923.98781 | H50: 856.05185 | I50: 797.35888 | J50: 746.14272 | K50: 701.06024 | L50: 661.07182 | M50: 625.36023
B51: 0.0725 | C51: 1381.6786 | D51: 1258.1543 | E51: 1154.8137 | F51: 1067.0834 | G51: 991.67484 | H51: 914.07823 | I51: 847.67345 | J51: 790.20204 | K51: 739.97493 | L51: 695.7036 | M51: 656.38802
B52: 0.075 | C52: 1535.5264 | D52: 1384.915 | E52: 1261.1027 | F52: 1157.5212 | G52: 1069.5865 | H52: 980.14151 | I52: 904.4221 | J52: 839.49406 | K52: 783.20389 | L52: 733.93536 | M52: 690.45179
B53: 0.0775 | C53: 1726.716 | D53: 1539.1131 | E53: 1388.1514 | F53: 1264.0512 | G53: 1160.2288 | H53: 1056.0356 | I53: 968.9233 | J53: 895.00981 | K53: 831.50667 | L53: 776.3592 | M53: 728.02007

Sheet FCFF
B2: Free Cash Flow Calculation
A5: # | B5: company overview
B7: JSW Steel has a consolidated steelmaking capacity of 35.7 MTPA, making it one of India's largest steel producers.
B8: The company is undertaking significant capital expenditure to increase steelmaking capacity from 35.7 MTPA to 51.5 MTPA by FY2031.
B9: The company operates 15+ manufacturing facilities across India and overseas.
B10: JSW Steel exports its products to more than 100 countries, giving it a strong global presence.
A13: # | B13: Key assumption & methodolgy
B15: Particulars | F15: Value | G15: Rational
B16: valutaion date | F16: 46176
B17: projection period
B18: revenue growth | F18: =Growth!D39 -> 0.095593751 | G18: considering median growth rate to prevent from outlier
B19: annual growth tappering | F19: 0.01
B20: terminal growth rate | F20: 0.065 | G20: based on world bank GDP growth rate data for India
B21: risk-free rate (Rf) | F21: 0.07 | G21: based on 10 year govt t bond
B22: Equity Risk Premium (ERP) | F22: =12%-F21 -> 0.05 | G22: CAGR of nifty 50 past 10 year is app. 12%
B23: Tax Rate | F23: 0.25 | G23: Effective tax rate based on historical data
A26: # | B26: Revenue projection and growth assumption
B28: Particulars | E28: 2027 | F28: =E28+1 -> 2028 | G28: =F28+1 -> 2029 | H28: =G28+1 -> 2030 | I28: =H28+1 -> 2031 | J28: =I28+1 -> 2032
B29: revenue growth % | E29: {=CHOOSE(E31,E32:J32,E33:J33,E34:J34)} -> 0.095593751 | F29: 0.085593751 | G29: 0.075593751 | H29: 0.065593751 | I29: 0.055593751 | J29: 0.045593751
B30: revenue | E30: =Historical!L7*(1+E29) -> 203199.77 | F30: =E30*(1+F29) -> 220592.4 | G30: =F30*(1+G29) -> 237267.81 | H30: =G30*(1+H29) -> 252831.1 | I30: =H30*(1+I29) -> 266886.93 | J30: =I30*(1+J29) -> 279055.3
B31: scenario | D31: Base | E31: =MATCH(D31,B32:B34,0) -> 1
B32: Base | E32: =F18 -> 0.095593751 | F32: =E32-tap_rate -> 0.085593751 | G32: =F32-tap_rate -> 0.075593751 | H32: =G32-tap_rate -> 0.065593751 | I32: =H32-tap_rate -> 0.055593751 | J32: =I32-tap_rate -> 0.045593751
B33: Best | E33: =E32+tap_rate -> 0.10559375 | F33: =F32+tap_rate -> 0.095593751 | G33: =G32+tap_rate -> 0.085593751 | H33: =H32+tap_rate -> 0.075593751 | I33: =I32+tap_rate -> 0.065593751 | J33: =J32+tap_rate -> 0.055593751
B34: Worst | E34: =E32-tap_rate -> 0.085593751 | F34: =F32-tap_rate -> 0.075593751 | G34: =G32-tap_rate -> 0.065593751 | H34: =H32-tap_rate -> 0.055593751 | I34: =I32-tap_rate -> 0.045593751 | J34: =J32-tap_rate -> 0.035593751
A37: # | B37: free cash flow projection
B39: particulars | E39: =E28 -> 2027 | F39: =F28 -> 2028 | G39: =G28 -> 2029 | H39: =H28 -> 2030 | I39: =I28 -> 2031 | J39: =J28 -> 2032
B40: Revenue | E40: =E30 -> 203199.77 | F40: =F30 -> 220592.4 | G40: =G30 -> 237267.81 | H40: =H30 -> 252831.1 | I40: =I30 -> 266886.93 | J40: =J30 -> 279055.3
B41: EBITDA Margin | E41: =Historical!M20 -> 0.14979781 | F41: =E41 -> 0.14979781 | G41: =F41 -> 0.14979781 | H41: =G41 -> 0.14979781 | I41: =H41 -> 0.14979781 | J41: =I41 -> 0.14979781
B42: EBITDA | E42: =E40*E41 -> 30438.881 | F42: =F40*F41 -> 33044.259 | G42: =G40*G41 -> 35542.199 | H42: =H40*H41 -> 37873.545 | I42: =I40*I41 -> 39979.077 | J42: =J40*J41 -> 41801.873
B43: Less : Deperication | E43: =FCFF!E40*(AVERAGE(Historical!C26:M26)) -> 10425.28 | F43: =FCFF!F40*(AVERAGE(Historical!D26:N26)) -> 11088.63 | G43: =FCFF!G40*(AVERAGE(Historical!E26:O26)) -> 12010.75 | H43: =FCFF!H40*(AVERAGE(Historical!F26:P26)) -> 12891.608 | I43: =FCFF!I40*(AVERAGE(Historical!G26:Q26)) -> 13344.587 | J43: =FCFF!J40*(AVERAGE(Historical!H26:R26)) -> 13552.827
B44: EBIT | E44: =E42-E43 -> 20013.601 | F44: =F42-F43 -> 21955.629 | G44: =G42-G43 -> 23531.449 | H44: =H42-H43 -> 24981.936 | I44: =I42-I43 -> 26634.49 | J44: =J42-J43 -> 28249.047
B45: Less : Tax | E45: =E44*tax_rate -> 5003.4002 | F45: =F44*tax_rate -> 5488.9072 | G45: =G44*tax_rate -> 5882.8623 | H45: =H44*tax_rate -> 6245.4841 | I45: =I44*tax_rate -> 6658.6225 | J45: =J44*tax_rate -> 7062.2616
B46: NOPAT | E46: =E44-E45 -> 15010.201 | F46: =F44-F45 -> 16466.722 | G46: =G44-G45 -> 17648.587 | H46: =H44-H45 -> 18736.452 | I46: =I44-I45 -> 19975.867 | J46: =J44-J45 -> 21186.785
B47: Add: Deperication | E47: =E43 -> 10425.28 | F47: =F43 -> 11088.63 | G47: =G43 -> 12010.75 | H47: =H43 -> 12891.608 | I47: =I43 -> 13344.587 | J47: =J43 -> 13552.827
B48: Less: Reinvestment | E48: =E46*Growth!$D$33 -> 13807.516 | F48: =F46*Growth!$D$33 -> 15147.334 | G48: =G46*Growth!$D$33 -> 16234.503 | H48: =H46*Growth!$D$33 -> 17235.203 | I48: =I46*Growth!$D$33 -> 18375.311 | J48: =J46*Growth!$D$33 -> 19489.204
B49: Free Cash Flow To Firm | E49: =E46+E47-E48 -> 11627.965 | F49: =F46+F47-F48 -> 12408.018 | G49: =G46+G47-G48 -> 13424.834 | H49: =H46+H47-H48 -> 14392.857 | I49: =I46+I47-I48 -> 14945.144 | J49: =J46+J47-J48 -> 15250.407

Sheet Growth
B2: Growth
A4: # | B4: Calculation return on capital
B5: Particulars | C5: ='Data Sheet'!B16 -> 42825 | D5: ='Data Sheet'!C16 -> 43190 | E5: ='Data Sheet'!D16 -> 43555 | F5: ='Data Sheet'!E16 -> 43921 | G5: ='Data Sheet'!F16 -> 44286 | H5: ='Data Sheet'!G16 -> 44651 | I5: ='Data Sheet'!H16 -> 45016 | J5: ='Data Sheet'!I16 -> 45382 | ... L5: ='Data Sheet'!K16 -> 46112
B7: EBIT | C7: =IFERROR(Historical!C19-Historical!C25,0) -> 8878 | D7: =IFERROR(Historical!D19-Historical!D25,0) -> 11529 | E7: =IFERROR(Historical!E19-Historical!E25,0) -> 14889 | F7: =IFERROR(Historical!F19-Historical!F25,0) -> 7567 | G7: =IFERROR(Historical!G19-Historical!G25,0) -> 15499 | H7: =IFERROR(Historical!H19-Historical!H25,0) -> 33113 | I7: =IFERROR(Historical!I19-Historical!I25,0) -> 10996 | J7: =IFERROR(Historical!J19-Historical!J25,0) -> 19985 | ... L7: =IFERROR(Historical!L19-Historical!L25,0) -> 19745
B8: Tax | C8: =Historical!C31 -> 1674 | D8: =Historical!D31 -> 1538 | E8: =Historical!E31 -> 3644 | F8: =Historical!F31 -> -906 | G8: =Historical!G31 -> 4142 | H8: =Historical!H31 -> 8807 | I8: =Historical!I31 -> 1516 | J8: =Historical!J31 -> 4407 | ... L8: =Historical!L31 -> 3742
B9: Nopat | C9: =C7-C8 -> 7204 | D9: =D7-D8 -> 9991 | E9: =E7-E8 -> 11245 | F9: =F7-F8 -> 8473 | G9: =G7-G8 -> 11357 | H9: =H7-H8 -> 24306 | I9: =I7-I8 -> 9480 | J9: =J7-J8 -> 15578 | ... L9: =L7-L8 -> 16003
B12: Particulars | C12: =C5 -> 42825 | D12: =D5 -> 43190 | E12: =E5 -> 43555 | F12: =F5 -> 43921 | G12: =G5 -> 44286 | H12: =H5 -> 44651 | I12: =I5 -> 45016 | J12: =J5 -> 45382 | ... L12: =L5 -> 46112
B14: BV of equity | C14: =SUM(Historical!C52:C53) -> 22647 | D14: =SUM(Historical!D52:D53) -> 27998 | E14: =SUM(Historical!E52:E53) -> 34795 | F14: =SUM(Historical!F52:F53) -> 36599 | G14: =SUM(Historical!G52:G53) -> 45610 | H14: =SUM(Historical!H52:H53) -> 67297 | I14: =SUM(Historical!I52:I53) -> 65695 | J14: =SUM(Historical!J52:J53) -> 77669 | ... L14: =SUM(Historical!L52:L53) -> 100053
B15: BV of debt | C15: ='Data Sheet'!B59 -> 43334 | D15: ='Data Sheet'!C59 -> 39393 | E15: ='Data Sheet'!D59 -> 47396 | F15: ='Data Sheet'!E59 -> 61423 | G15: ='Data Sheet'!F59 -> 66727 | H15: ='Data Sheet'!G59 -> 72237 | I15: ='Data Sheet'!H59 -> 80853 | J15: ='Data Sheet'!I59 -> 87984 | ... L15: ='Data Sheet'!K59 -> 99310
B16: cash | C16: ='Data Sheet'!B69 -> 1485 | D16: ='Data Sheet'!C69 -> 1063 | E16: ='Data Sheet'!D69 -> 6187 | F16: ='Data Sheet'!E69 -> 12003 | G16: ='Data Sheet'!F69 -> 12813 | H16: ='Data Sheet'!G69 -> 17383 | I16: ='Data Sheet'!H69 -> 20714 | J16: ='Data Sheet'!I69 -> 12348 | ... L16: ='Data Sheet'!K69 -> 40989
B17: BV of Capital | C17: =SUM(C14:C15)-C16 -> 64496 | D17: =SUM(D14:D15)-D16 -> 66328 | E17: =SUM(E14:E15)-E16 -> 76004 | F17: =SUM(F14:F15)-F16 -> 86019 | G17: =SUM(G14:G15)-G16 -> 99524 | H17: =SUM(H14:H15)-H16 -> 122151 | I17: =SUM(I14:I15)-I16 -> 125834 | J17: =SUM(J14:J15)-J16 -> 153305 | ... L17: =SUM(L14:L15)-L16 -> 158374
B20: Return on capital | C20: =C9/C17 -> 0.11169685 | D20: =D9/D17 -> 0.1506302 | E20: =E9/E17 -> 0.14795274 | F20: =F9/F17 -> 0.098501494 | G20: =G9/G17 -> 0.11411318 | H20: =H9/H17 -> 0.19898323 | I20: =I9/I17 -> 0.075337349 | J20: =J9/J17 -> 0.10161443 | ... L20: =L9/L17 -> 0.10104563
A23: # | B23: Calculation of Reinvestment Rate
B24: Particulars | C24: =C12 -> 42825 | D24: =D12 -> 43190 | E24: =E12 -> 43555 | F24: =F12 -> 43921 | G24: =G12 -> 44286 | H24: =H12 -> 44651 | I24: =I12 -> 45016 | J24: =J12 -> 45382 | ... L24: =L12 -> 46112
B26: Net Cap expenditure | D26: =Historical!D58-Historical!C58+Historical!D25 -> 2505 | E26: =Historical!E58-Historical!D58+Historical!E25 -> 8837 | F26: =Historical!F58-Historical!E58+Historical!F25 -> 3687 | G26: =Historical!G58-Historical!F58+Historical!G25 -> 7511 | H26: =Historical!H58-Historical!G58+Historical!H25 -> 40964 | I26: =Historical!I58-Historical!H58+Historical!I25 -> 12046 | J26: =Historical!J58-Historical!I58+Historical!J25 -> 16181 | K26: =Historical!K58-Historical!J58+Historical!K25 -> 21314 | L26: =Historical!L58-Historical!K58+Historical!L25 -> 2687
B27: working capital | C27: =Historical!C67-Historical!C55 -> -4995 | D27: =Historical!D67-Historical!D55 -> -6218 | E27: =Historical!E67-Historical!E55 -> -4711 | F27: =Historical!F67-Historical!F55 -> -3517 | G27: =Historical!G67-Historical!G55 -> -3278 | H27: =Historical!H67-Historical!H55 -> 1676 | I27: =Historical!I67-Historical!I55 -> -3008 | J27: =Historical!J67-Historical!J55 -> -4534 | ... L27: =Historical!L67-Historical!L55 -> 14701
B28: Change in working capital | D28: =D27-C27 -> -1223 | E28: =E27-D27 -> 1507 | F28: =F27-E27 -> 1194 | G28: =G27-F27 -> 239 | H28: =H27-G27 -> 4954 | I28: =I27-H27 -> -4684 | J28: =J27-I27 -> -1526 | K28: =K27-J27 -> -1007 | L28: =L27-K27 -> 20242
B29: Reinvestment | D29: =D26+D28 -> 1282 | E29: =E26+E28 -> 10344 | F29: =F26+F28 -> 4881 | G29: =G26+G28 -> 7750 | H29: =H26+H28 -> 45918 | I29: =I26+I28 -> 7362 | J29: =J26+J28 -> 14655 | K29: =K26+K28 -> 20307 | L29: =L26+L28 -> 22929
B32: Reinvestment Rate | D32: =D29/D9 -> 0.12831548 | E32: =E29/E9 -> 0.9198755 | F32: =F29/F9 -> 0.57606515 | G32: =G29/G9 -> 0.68239852 | H32: =H29/H9 -> 1.8891632 | I32: =I29/I9 -> 0.77658228 | J32: =J29/J9 -> 0.94074978 | K32: =K29/K9 -> 1.716568 | L32: =L29/L9 -> 1.4327939
B33: median | D33: =MEDIAN(D32:L32) -> 0.9198755
A36: # | B36: calculation of expected growth
B37: growth | D37: =D32*D20 -> 0.019328187 | E37: =E32*E20 -> 0.1360981 | F37: =F32*F20 -> 0.056743278 | G37: =G32*G20 -> 0.077870664 | H37: =H32*H20 -> 0.37591178 | I37: =I32*I20 -> 0.05850565 | J37: =J32*J20 -> 0.095593751 | K37: =K32*K20 -> 0.12310033 | L37: =L32*L20 -> 0.14477755
B38: average | D38: =AVERAGE(D37:L37) -> 0.12088103
B39: median | D39: =MEDIAN(D37:L37) -> 0.095593751

Sheet WACC
B2: Weighted average cost of capital
B4: all figures are in inr unless stated altrnatives
B6: peer comps
B8: name of the comp | C8: country | D8: total debt | E8: total equity | F8: tax rate 1 | G8: debt/ equity | H8: debt/ capital | I8: levered beta 2 | J8: unlivered beta 3
B10: TATA steel | C10: India | D10: 92381.68 | E10: 262928.05 | F10: =tax_rate -> 0.25 | G10: =D10/E10 -> 0.35135726 | H10: =D10/(E10+D10) -> 0.26000324 | I10: 1.1 | J10: =I10/(1+(1-F10)*G10) -> 0.87058518
B11: Jindal steel | C11: India | D11: 22609.55 | E11: 122767.55 | F11: =tax_rate -> 0.25 | G11: =D11/E11 -> 0.18416552 | H11: =D11/(E11+D11) -> 0.15552346 | I11: 1.12 | J11: =I11/(1+(1-F11)*G11) -> 0.98407543
B12: SAIL | C12: India | D12: 31927.71 | E12: 84835.28 | F12: =tax_rate -> 0.25 | G12: =D12/E12 -> 0.37634944 | H12: =D12/(E12+D12) -> 0.27344033 | I12: 1.14 | J12: =I12/(1+(1-F12)*G12) -> 0.88905382
B13: jidnal stain | C13: India | D13: 7460.33 | E13: 56604.32 | F13: =tax_rate -> 0.25 | G13: =D13/E13 -> 0.13179789 | H13: =D13/(E13+D13) -> 0.11645002 | I13: 1.14 | J13: =I13/(1+(1-F13)*G13) -> 1.0374497
B14: sharda energy | C14: India | D14: 2631.92 | E14: 18318.6 | F14: =tax_rate -> 0.25 | G14: =D14/E14 -> 0.14367473 | H14: =D14/(E14+D14) -> 0.12562552 | I14: 0.996 | J14: =I14/(1+(1-F14)*G14) -> 0.89911493
C16: average | D16: =AVERAGE(D10:D14) -> 31402.238 | E16: =AVERAGE(E10:E14) -> 109090.76 | F16: =AVERAGE(F10:F14) -> 0.25 | G16: =AVERAGE(G10:G14) -> 0.23746897 | H16: =AVERAGE(H10:H14) -> 0.18620851 | I16: =AVERAGE(I10:I14) -> 1.0992 | J16: =AVERAGE(J10:J14) -> 0.93605582
C17: median | D17: =MEDIAN(D10:D14) -> 22609.55 | E17: =MEDIAN(E10:E14) -> 84835.28 | F17: =MEDIAN(F10:F14) -> 0.25 | G17: =MEDIAN(G10:G14) -> 0.18416552 | H17: =MEDIAN(H10:H14) -> 0.15552346 | I17: =MEDIAN(I10:I14) -> 1.12 | J17: =MEDIAN(J10:J14) -> 0.89911493
B20: cost of debt | H20: cost of equity
B22: pre-tax cost of debt | E22: 0.084 | H22: riske free rate | M22: =RF -> 0.07
B23: tax rate | E23: =tax_rate -> 0.25 | H23: equity risk permium | M23: =ERP -> 0.05
B24: after tax cost of debt | E24: =E22*(1-E23) -> 0.063 | H24: levered beta 4 | M24: =M33 -> 1.0788331
H25: Cost of equity | M25: =M22+(M23*M24) -> 0.12394165
B28: capital structure | H28: levered beta
D30: current | E30: taget 5. | H30: comps median unlivered beta | M30: =J17 -> 0.89911493
B31: total debt | C31: ='Data Sheet'!K59 -> 99310 | D31: =C31/C33 -> 0.24113791 | E31: =D17 -> 22609.55 | H31: target debt/equity | M31: =E31/E32 -> 0.26651117
B32: markt capitalisation | C32: ='Data Sheet'!B9 -> 312529.02 | D32: =C32/C33 -> 0.75886209 | E32: =E17 -> 84835.28 | H32: tax rate | M32: =E23 -> 0.25
B33: total capitalisation | C33: =C32+C31 -> 411839.02 | D33: =D31+D32 -> 1 | E33: 1 | M33: =M30*(1+(1-M32)*M31) -> 1.0788331
B36: Debt /equity | D36: =D31/D32 -> 0.31776249 | E36: =E31/E32 -> 0.26651117 | H36: Weighted Average cost of capital
L38: Total cost | M38: Total weight
B39: 1. Tax Rate considered as Marginal Tax Rate for the country
B40: 2. Levered Beta is based on long term beta | H40: debt capital | L40: =E24 -> 0.063 | M40: =E31/SUM(E31:E32) -> 0.21042939
B41: 3. Unlevered Beta = Levered Beta/(1+(1-Tax Rate) x Debt/Equity) | H41: equity capital | L41: =M25 -> 0.12394165 | M41: =E32/SUM(E31:E32) -> 0.78957061
B42: 4. Levered Beta = Unlevered Beta*(1+(1-Tax Rate) x Debt/Equity) | H42: Weight average cost of capital | L42: =(L40*M40)+(L41*M41) -> 0.11111774
B43: 5. Target debt/equity based on peers

Sheet DuPont Analysis
B3: ='[2]Data Sheet'!B1 -> JSW STEEL LTD
B4: (JSW Steel Ltd | BSE Code: 500228)
B5: ="INR "&'[2]Data Sheet'!B8 -> INR 1284
B6: 52 Week (High - INR 1231 & Low - INR 1210)
B8: About the company
B10: JSW Steel Limited is an Indian multinational steel producer based in Mumbai and is a flagship company of the JSW Group. After the merger of Bhushan Power & Steel, and Ispat Steel and Jindal Vijayanagar Steel Limited, JSW Steel became one of India's largest private sector steel companies. JSW Steel's history can be traced back to 1982, when the Jindal Group acquired Piramal Steel Limited, which operated a mini steel mill at Tarapur in Maharashtra and renamed it as Jindal Iron and Steel Company (JISCO). Soon after the acquisition the group set up its first steel plant in 1982 at Vasind, near Mumbai.As of July 2023, the installed with a production capacity of 29.7 MTPA in India and the United States. The company is aiming to boost the total steel production capacity to 38.5 MTPA by the financial year 2025.
B19: Financial Summary
B67: Return on Equity (ROE)
B68: Particulars | C68: ='[2]Data Sheet'!E56 -> 43921 | D68: ='[2]Data Sheet'!F56 -> 44286 | E68: ='[2]Data Sheet'!G56 -> 44651 | F68: ='[2]Data Sheet'!H56 -> 45016 | G68: ='[2]Data Sheet'!I56 -> 45382 | H68: ='[2]Data Sheet'!J56 -> 45747 | I68: ='[2]Data Sheet'!K56 -> 46112
B70: Net Profit | C70: ='[2]Data Sheet'!E30 -> 4030 | D70: ='[2]Data Sheet'!F30 -> 7911 | E70: ='[2]Data Sheet'!G30 -> 20665 | F70: ='[2]Data Sheet'!H30 -> 4144 | G70: ='[2]Data Sheet'!I30 -> 8812 | H70: ='[2]Data Sheet'!J30 -> 3504 | I70: ='[2]Data Sheet'!K30 -> 22316
B71: Averge Shareholder Equity | C71: =('[2]Data Sheet'!E57+'[2]Data Sheet'!E58)+('[2]Data Sheet'!D57+'[2]Data Sheet'!D58)/2 -> 53996.5 | D71: =('[2]Data Sheet'!F57+'[2]Data Sheet'!F58)+('[2]Data Sheet'!E57+'[2]Data Sheet'!E58)/2 -> 63909.5 | E71: =('[2]Data Sheet'!G57+'[2]Data Sheet'!G58)+('[2]Data Sheet'!F57+'[2]Data Sheet'!F58)/2 -> 90102 | F71: =('[2]Data Sheet'!H57+'[2]Data Sheet'!H58)+('[2]Data Sheet'!G57+'[2]Data Sheet'!G58)/2 -> 99343.5 | G71: =('[2]Data Sheet'!I57+'[2]Data Sheet'!I58)+('[2]Data Sheet'!H57+'[2]Data Sheet'!H58)/2 -> 110516.5 | H71: =('[2]Data Sheet'!J57+'[2]Data Sheet'!J58)+('[2]Data Sheet'!I57+'[2]Data Sheet'!I58)/2 -> 118330.5 | I71: =('[2]Data Sheet'!K57+'[2]Data Sheet'!K58)+('[2]Data Sheet'!J57+'[2]Data Sheet'!J58)/2 -> 139801
B72: Retun On Equity | C72: =C70/C71 -> 0.074634467 | D72: =D70/D71 -> 0.12378441 | E72: =E70/E71 -> 0.22935118 | F72: =F70/F71 -> 0.041713851 | G72: =G70/G71 -> 0.0797347 | H72: =H70/H71 -> 0.029611977 | I72: =I70/I71 -> 0.1596269
B74: (ROE)- DuPont Equation
B75: Particulars | C75: =C68 -> 43921 | D75: =D68 -> 44286 | E75: =E68 -> 44651 | F75: =F68 -> 45016 | G75: =G68 -> 45382 | H75: =H68 -> 45747 | I75: =I68 -> 46112
B77: Net Profit | C77: =C70 -> 4030 | D77: =D70 -> 7911 | E77: =E70 -> 20665 | F77: =F70 -> 4144 | G77: =G70 -> 8812 | H77: =H70 -> 3504 | I77: =I70 -> 22316
B78: Revenue | C78: ='[2]Data Sheet'!E17 -> 73326 | D78: ='[2]Data Sheet'!F17 -> 79839 | E78: ='[2]Data Sheet'!G17 -> 146371 | F78: ='[2]Data Sheet'!H17 -> 165960 | G78: ='[2]Data Sheet'!I17 -> 175006 | H78: ='[2]Data Sheet'!J17 -> 168824 | I78: ='[2]Data Sheet'!K17 -> 185470
B79: Net Profit Margin (A) | C79: =C77/C78 -> 0.054960041 | D79: =D77/D78 -> 0.099086912 | E79: =E77/E78 -> 0.14118234 | F79: =F77/F78 -> 0.024969872 | G79: =G77/G78 -> 0.050352559 | H79: =H77/H78 -> 0.020755343 | I79: =I77/I78 -> 0.12032135
B81: Revenue | C81: =C78 -> 73326 | D81: =D78 -> 79839 | E81: =E78 -> 146371 | F81: =F78 -> 165960 | G81: =G78 -> 175006 | H81: =H78 -> 168824 | I81: =I78 -> 185470
B82: Average Total Assets | C82: =('[2]Data Sheet'!E66+'[2]Data Sheet'!D66)/2 -> 123308.5 | D82: =('[2]Data Sheet'!F66+'[2]Data Sheet'!E66)/2 -> 139491.5 | E82: =('[2]Data Sheet'!G66+'[2]Data Sheet'!F66)/2 -> 171824 | F82: =('[2]Data Sheet'!H66+'[2]Data Sheet'!G66)/2 -> 203512 | G82: =('[2]Data Sheet'!I66+'[2]Data Sheet'!H66)/2 -> 219218.5 | H82: =('[2]Data Sheet'!J66+'[2]Data Sheet'!I66)/2 -> 234171.5 | I82: =('[2]Data Sheet'!K66+'[2]Data Sheet'!J66)/2 -> 255060.5
B83: Assest Turnover Ratio (B) | C83: =C81/C82 -> 0.59465487 | D83: =D81/D82 -> 0.57235746 | E83: =E81/E82 -> 0.85186586 | F83: =F81/F82 -> 0.81548017 | G83: =G81/G82 -> 0.79831766 | H83: =H81/H82 -> 0.7209417 | I83: =I81/I82 -> 0.72716081
B85: Average Total Asset | C85: =C82 -> 123308.5 | D85: =D82 -> 139491.5 | E85: =E82 -> 171824 | F85: =F82 -> 203512 | G85: =G82 -> 219218.5 | H85: =H82 -> 234171.5 | I85: =I82 -> 255060.5
B86: Total Equity | C86: =C71 -> 53996.5 | D86: =D71 -> 63909.5 | E86: =E71 -> 90102 | F86: =F71 -> 99343.5 | G86: =G71 -> 110516.5 | H86: =H71 -> 118330.5 | I86: =I71 -> 139801
B87: Equity Multiplyer (C) | C87: =C85/C86 -> 2.2836388 | D87: =D85/D86 -> 2.1826411 | E87: =E85/E86 -> 1.9069943 | F87: =F85/F86 -> 2.0485689 | G87: =G85/G86 -> 1.9835816 | H87: =H85/H86 -> 1.9789615 | I87: =I85/I86 -> 1.824454
B89: Retun On Equity (A*B*C) | C89: =C79*C83*C87 -> 0.074634467 | D89: =D79*D83*D87 -> 0.12378441 | E89: =E79*E83*E87 -> 0.22935118 | F89: =F79*F83*F87 -> 0.041713851 | G89: =G79*G83*G87 -> 0.0797347 | H89: =H79*H83*H87 -> 0.029611977 | I89: =I79*I83*I87 -> 0.1596269
B92: Return On Assest (ROA)
B93: Particulars | C93: ='[2]Data Sheet'!E81 -> 43921 | D93: ='[2]Data Sheet'!F81 -> 44286 | E93: ='[2]Data Sheet'!G81 -> 44651 | F93: ='[2]Data Sheet'!H81 -> 45016 | G93: ='[2]Data Sheet'!I81 -> 45382 | H93: ='[2]Data Sheet'!J81 -> 45747 | I93: ='[2]Data Sheet'!K81 -> 46112
B95: Net Profit | C95: =C70 -> 4030 | D95: =D70 -> 7911 | E95: =E70 -> 20665 | F95: =F70 -> 4144 | G95: =G70 -> 8812 | H95: =H70 -> 3504 | I95: =I70 -> 22316
B96: Averge Total Assest | C96: =C82 -> 123308.5 | D96: =D82 -> 139491.5 | E96: =E82 -> 171824 | F96: =F82 -> 203512 | G96: =G82 -> 219218.5 | H96: =H82 -> 234171.5 | I96: =I82 -> 255060.5
B97: Retun On Asset | C97: =C95/C96 -> 0.032682256 | D97: =D95/D96 -> 0.056713133 | E97: =E95/E96 -> 0.12026841 | F97: =F95/F96 -> 0.020362436 | G97: =G95/G96 -> 0.040197337 | H97: =H95/H96 -> 0.014963392 | I97: =I95/I96 -> 0.087492967
B99: ROA - DuPont Equation
B100: Particulars | C100: =C93 -> 43921 | D100: =D93 -> 44286 | E100: =E93 -> 44651 | F100: =F93 -> 45016 | G100: =G93 -> 45382 | H100: =H93 -> 45747 | I100: =I93 -> 46112
B102: Net Profit | C102: =C77 -> 4030 | D102: =D77 -> 7911 | E102: =E77 -> 20665 | F102: =F77 -> 4144 | G102: =G77 -> 8812 | H102: =H77 -> 3504 | I102: =I77 -> 22316
B103: Revenue | C103: =C78 -> 73326 | D103: =D78 -> 79839 | E103: =E78 -> 146371 | F103: =F78 -> 165960 | G103: =G78 -> 175006 | H103: =H78 -> 168824 | I103: =I78 -> 185470
B104: Net Profit Marin (A) | C104: =C102/C103 -> 0.054960041 | D104: =D102/D103 -> 0.099086912 | E104: =E102/E103 -> 0.14118234 | F104: =F102/F103 -> 0.024969872 | G104: =G102/G103 -> 0.050352559 | H104: =H102/H103 -> 0.020755343 | I104: =I102/I103 -> 0.12032135
B106: Revenue | C106: =C81 -> 73326 | D106: =D81 -> 79839 | E106: =E81 -> 146371 | F106: =F81 -> 165960 | G106: =G81 -> 175006 | H106: =H81 -> 168824 | I106: =I81 -> 185470
B107: Average Total Assets | C107: =C85 -> 123308.5 | D107: =D85 -> 139491.5 | E107: =E85 -> 171824 | F107: =F85 -> 203512 | G107: =G85 -> 219218.5 | H107: =H85 -> 234171.5 | I107: =I85 -> 255060.5
B108: Assest Turnover Ratio (B) | C108: =C106/C107 -> 0.59465487 | D108: =D106/D107 -> 0.57235746 | E108: =E106/E107 -> 0.85186586 | F108: =F106/F107 -> 0.81548017 | G108: =G106/G107 -> 0.79831766 | H108: =H106/H107 -> 0.7209417 | I108: =I106/I107 -> 0.72716081
B110: Retun On Asset (A*B) | C110: =C104*C108 -> 0.032682256 | D110: =D104*D108 -> 0.056713133 | E110: =E104*E108 -> 0.12026841 | F110: =F104*F108 -> 0.020362436 | G110: =G104*G108 -> 0.040197337 | H110: =H104*H108 -> 0.014963392 | I110: =I104*I108 -> 0.087492967

Sheet Altman z score
B2: Altman's Z Score Analysis Calculation
B5: Particulars | C5: ='[3]Data Sheet'!E56 -> 43921 | D5: ='[3]Data Sheet'!F56 -> 44286 | E5: ='[3]Data Sheet'!G56 -> 44651 | F5: ='[3]Data Sheet'!H56 -> 45016 | G5: ='[3]Data Sheet'!I56 -> 45382 | H5: ='[3]Data Sheet'!J56 -> 45747 | I5: ='[3]Data Sheet'!K56 -> 46112
B6: Working Capital / Total Assets
B8: Working Capital | C8: ='[3]Data Sheet'!E65-'[3]Data Sheet'!E60 -> 7487 | D8: ='[3]Data Sheet'!F65-'[3]Data Sheet'!F60 -> 7427 | E8: ='[3]Data Sheet'!G65-'[3]Data Sheet'!G60 -> 17809 | F8: ='[3]Data Sheet'!H65-'[3]Data Sheet'!H60 -> 15124 | G8: ='[3]Data Sheet'!I65-'[3]Data Sheet'!I60 -> 16270 | H8: ='[3]Data Sheet'!J65-'[3]Data Sheet'!J60 -> 17558 | I8: ='[3]Data Sheet'!K65-'[3]Data Sheet'!K60 -> 49701
B9: Total Assets | C9: ='[3]Data Sheet'!E66 -> 131820 | D9: ='[3]Data Sheet'!F66 -> 147163 | E9: ='[3]Data Sheet'!G66 -> 196485 | F9: ='[3]Data Sheet'!H66 -> 210539 | G9: ='[3]Data Sheet'!I66 -> 227898 | H9: ='[3]Data Sheet'!J66 -> 240445 | I9: ='[3]Data Sheet'!K66 -> 269676
B10: Working Capital / Total Assets (A) | C10: =C8/C9 -> 0.056797148 | D10: =D8/D9 -> 0.050467849 | E10: =E8/E9 -> 0.090637962 | F10: =F8/F9 -> 0.071834672 | G10: =G8/G9 -> 0.071391587 | H10: =H8/H9 -> 0.073022937 | I10: =I8/I9 -> 0.18429894
B12: Retained Earnings / Total Assets
B13: Retained Earnings | C13: =[3]Historical!F48*[3]Historical!F37 -> 3317 | D13: =[3]Historical!G48*[3]Historical!G37 -> 5910 | E13: =[3]Historical!H48*[3]Historical!H37 -> 15715.65 | F13: =[3]Historical!I48*[3]Historical!I37 -> 3115.6 | G13: =[3]Historical!J48*[3]Historical!J37 -> 6746.5 | H13: =[3]Historical!K48*[3]Historical!K37 -> 2637 | I13: =[3]Historical!L48*[3]Historical!L37 -> 23342.5
B14: Total Assets | C14: =C9 -> 131820 | D14: =D9 -> 147163 | E14: =E9 -> 196485 | F14: =F9 -> 210539 | G14: =G9 -> 227898 | H14: =H9 -> 240445 | I14: =I9 -> 269676
B15: Retained Earnings / Total Assets (B) | C15: =C13/C14 -> 0.025163101 | D15: =D13/D14 -> 0.040159551 | E15: =E13/E14 -> 0.079983968 | F15: =F13/F14 -> 0.014798208 | G15: =G13/G14 -> 0.029603156 | H15: =H13/H14 -> 0.010967165 | I15: =I13/I14 -> 0.086557573
B17: EBIT / Total Assets
B18: EBIT | C18: =[3]Historical!F22-[3]Historical!F28 -> 7278 | D18: =[3]Historical!G22-[3]Historical!G28 -> 15972 | E18: =[3]Historical!H22-[3]Historical!H28 -> 34713 | F18: =[3]Historical!I22-[3]Historical!I28 -> 12557 | G18: =[3]Historical!J22-[3]Historical!J28 -> 21485 | H18: =[3]Historical!K22-[3]Historical!K28 -> 13489 | I18: =[3]Historical!L22-[3]Historical!L28 -> 38352
B19: Total Assets | C19: =C14 -> 131820 | D19: =D14 -> 147163 | E19: =E14 -> 196485 | F19: =F14 -> 210539 | G19: =G14 -> 227898 | H19: =H14 -> 240445 | I19: =I14 -> 269676
B20: EBIT/Total Assets (C) | C20: =C18/C19 -> 0.055211652 | D20: =D18/D19 -> 0.10853272 | E20: =E18/E19 -> 0.17666997 | F20: =F18/F19 -> 0.059642157 | G20: =G18/G19 -> 0.094274632 | H20: =H18/H19 -> 0.056100148 | I20: =I18/I19 -> 0.1422151
B22: Market Cap / Long term Liabilities
B23: Market Cap | C23: ='[3]Data Sheet'!E90*'[3]Data Sheet'!E70/10000000 -> 44046.28 | D23: ='[3]Data Sheet'!F90*'[3]Data Sheet'!F70/10000000 -> 141273.57 | E23: ='[3]Data Sheet'!G90*'[3]Data Sheet'!G70/10000000 -> 221011.46 | F23: ='[3]Data Sheet'!H90*'[3]Data Sheet'!H70/10000000 -> 207837.61 | G23: ='[3]Data Sheet'!I90*'[3]Data Sheet'!I70/10000000 -> 253427.04 | H23: ='[3]Data Sheet'!J90*'[3]Data Sheet'!J70/10000000 -> 324552.68 | I23: ='[3]Data Sheet'!B9 -> 313996.29
B24: Long term Liabilities | C24: ='[3]Data Sheet'!E59 -> 61423 | D24: ='[3]Data Sheet'!F59 -> 66727 | E24: ='[3]Data Sheet'!G59 -> 72237 | F24: ='[3]Data Sheet'!H59 -> 80853 | G24: ='[3]Data Sheet'!I59 -> 87984 | H24: ='[3]Data Sheet'!J59 -> 98752 | I24: ='[3]Data Sheet'!K59 -> 99310
B25: Market Cap / Long term Liabilities (D) | C25: =C23/C24 -> 0.71709751 | D25: =D23/D24 -> 2.1171876 | E25: =E23/E24 -> 3.0595327 | F25: =F23/F24 -> 2.5705615 | G25: =G23/G24 -> 2.8803765 | H25: =H23/H24 -> 3.2865428 | I25: =I23/I24 -> 3.1617792
B27: Sales / Total Assets
B28: Total Sales | C28: ='[3]Data Sheet'!E42 -> 39684 | D28: ='[3]Data Sheet'!F42 -> 41378 | E28: ='[3]Data Sheet'!G42 -> 44819 | F28: ='[3]Data Sheet'!H42 -> 43147 | G28: ='[3]Data Sheet'!I42 -> 45152 | H28: ='[3]Data Sheet'!J42 -> 45991 | I28: ='[3]Data Sheet'!K42 -> 51180
B29: Total Assets | C29: =C19 -> 131820 | D29: =D19 -> 147163 | E29: =E19 -> 196485 | F29: =F19 -> 210539 | G29: =G19 -> 227898 | H29: =H19 -> 240445 | I29: =I19 -> 269676
B30: Return on Asset (E) | C30: =C28/C29 -> 0.30104688 | D30: =D28/D29 -> 0.28117122 | E30: =E28/E29 -> 0.22810393 | F30: =F28/F29 -> 0.2049359 | G30: =G28/G29 -> 0.19812372 | H30: =H28/H29 -> 0.19127451 | I30: =I28/I29 -> 0.1897833
B33: Altman's Z Score
B35: Particulars | C35: =C5 -> 43921 | D35: =D5 -> 44286 | E35: =E5 -> 44651 | F35: =F5 -> 45016 | G35: =G5 -> 45382 | H35: =H5 -> 45747 | I35: =I5 -> 46112
B36: Final Score | C36: =(C10*1.2)+(C15*1.4)+(C20*3.3)+(C25*0.6)*(C30*1) -> 0.41511135 | D36: =(D10*1.2)+(D15*1.4)+(D20*3.3)+(D25*0.6)*(D30*1) -> 0.83211807 | E36: =(E10*1.2)+(E15*1.4)+(E20*3.3)+(E25*0.6)*(E30*1) -> 1.2224889 | F36: =(F10*1.2)+(F15*1.4)+(F20*3.3)+(F25*0.6)*(F30*1) -> 0.61981842 | G36: =(G10*1.2)+(G15*1.4)+(G20*3.3)+(G25*0.6)*(G30*1) -> 0.78062315 | H36: =(H10*1.2)+(H15*1.4)+(H20*3.3)+(H25*0.6)*(H30*1) -> 0.66529117 | I36: =(I10*1.2)+(I15*1.4)+(I20*3.3)+(I25*0.6)*(I30*1) -> 1.1716809
B38: Financial Stability | C38: =IF(C36<1.81," Distressed",IF(C36>3,"Strong","Grey Zone")) -> Distressed | D38: =IF(D36<1.81," Distressed",IF(D36>3,"Strong","Grey Zone")) -> Distressed | E38: =IF(E36<1.81," Distressed",IF(E36>3,"Strong","Grey Zone")) -> Distressed | F38: =IF(F36<1.81," Distressed",IF(F36>3,"Strong","Grey Zone")) -> Distressed | G38: =IF(G36<1.81," Distressed",IF(G36>3,"Strong","Grey Zone")) -> Distressed | H38: =IF(H36<1.81," Distressed",IF(H36>3,"Strong","Grey Zone")) -> Distressed | I38: =IF(I36<1.81," Distressed",IF(I36>3,"Strong","Grey Zone")) -> Distressed

Sheet Benish Model
B2: Benish M-Score Analysis Calculation
B5: Particulars | C5: ='[1]Data sheet'!E56 -> 43921 | D5: ='[1]Data sheet'!F56 -> 44286 | E5: ='[1]Data sheet'!G56 -> 44651 | F5: ='[1]Data sheet'!H56 -> 45016 | G5: ='[1]Data sheet'!I56 -> 45382 | H5: ='[1]Data sheet'!J56 -> 45747 | I5: ='[1]Data sheet'!K56 -> 46112
B7: Days Sales Recivable Index
B8: Recivable/Sales (current year) | C8: ='Data Sheet'!E67/'Data Sheet'!E17 -> 0.061437962 | D8: ='Data Sheet'!F67/'Data Sheet'!F17 -> 0.056188079 | E8: ='Data Sheet'!G67/'Data Sheet'!G17 -> 0.050945884 | F8: ='Data Sheet'!H67/'Data Sheet'!H17 -> 0.042986262 | G8: ='Data Sheet'!I67/'Data Sheet'!I17 -> 0.04312995 | H8: ='Data Sheet'!J67/'Data Sheet'!J17 -> 0.049844809 | I8: ='Data Sheet'!K67/'Data Sheet'!K17 -> 0.060710627
B9: Recivable/Sales (previous year) | C9: ='Data Sheet'!D67/'Data Sheet'!D17 -> 0.084476798 | D9: ='Data Sheet'!E67/'Data Sheet'!E17 -> 0.061437962 | E9: ='Data Sheet'!F67/'Data Sheet'!F17 -> 0.056188079 | F9: ='Data Sheet'!G67/'Data Sheet'!G17 -> 0.050945884 | G9: ='Data Sheet'!H67/'Data Sheet'!H17 -> 0.042986262 | H9: ='Data Sheet'!I67/'Data Sheet'!I17 -> 0.04312995 | I9: ='Data Sheet'!J67/'Data Sheet'!J17 -> 0.049844809
B10: Days Sales Recivable Index | C10: =C8/C9 -> 0.72727617 | D10: =D8/D9 -> 0.91454984 | E10: =E8/E9 -> 0.90670273 | F10: =F8/F9 -> 0.84376319 | G10: =G8/G9 -> 1.0033427 | H10: =H8/H9 -> 1.155689 | I10: =I8/I9 -> 1.217993
B12: Gross Margin Index
B13: Gross Margin (previous year) | C13: =Historical!E14 -> 0.25780761 | D13: =Historical!F14 -> 0.20786624 | E13: =Historical!G14 -> 0.282982 | F13: =Historical!H14 -> 0.29099343 | G13: =Historical!I14 -> 0.1508496 | H13: =Historical!J14 -> 0.19373621 | I13: =Historical!K14 -> 0.17128489
B14: Gross Margin (Currrent year) | C14: =Historical!F14 -> 0.20786624 | D14: =Historical!G14 -> 0.282982 | E14: =Historical!H14 -> 0.29099343 | F14: =Historical!I14 -> 0.1508496 | G14: =Historical!J14 -> 0.19373621 | H14: =Historical!K14 -> 0.17128489 | I14: =Historical!L14 -> 0.36362754
B15: Gross Margin Index | C15: =C13/C14 -> 1.2402573 | D15: =D13/D14 -> 0.7345564 | E15: =E13/E14 -> 0.97246868 | F15: =F13/F14 -> 1.9290302 | G15: =G13/G14 -> 0.77863399 | H15: =H13/H14 -> 1.1310759 | I15: =I13/I14 -> 0.47104487
B17: Asset Quality Index
B18: Asset Quality (current year) | C18: =(Historical!F69-Historical!F67-Historical!F58)/Historical!F69 -> 0.29930208 | D18: =(Historical!G69-Historical!G67-Historical!G58)/Historical!G69 -> 0.34450235 | E18: =(Historical!H69-Historical!H67-Historical!H58)/Historical!H69 -> 0.19328702 | F18: =(Historical!I69-Historical!I67-Historical!I58)/Historical!I69 -> 0.21423109 | G18: =(Historical!J69-Historical!J67-Historical!J58)/Historical!J69 -> 0.25329753 | H18: =(Historical!K69-Historical!K67-Historical!K58)/Historical!K69 -> 0.2467217 | I18: =(Historical!L69-Historical!L67-Historical!L58)/Historical!L69 -> 0.24885418
B19: Asset Quality (previous year) | C19: =(Historical!E69-Historical!E67-Historical!E58)/Historical!E69 -> 0.21131214 | D19: =(Historical!F69-Historical!F67-Historical!F58)/Historical!F69 -> 0.29930208 | E19: =(Historical!G69-Historical!G67-Historical!G58)/Historical!G69 -> 0.34450235 | F19: =(Historical!H69-Historical!H67-Historical!H58)/Historical!H69 -> 0.19328702 | G19: =(Historical!I69-Historical!I67-Historical!I58)/Historical!I69 -> 0.21423109 | H19: =(Historical!J69-Historical!J67-Historical!J58)/Historical!J69 -> 0.25329753 | I19: =(Historical!K69-Historical!K67-Historical!K58)/Historical!K69 -> 0.2467217
B20: Asset Quality Index | C20: =C18/C19 -> 1.4163979 | D20: =D18/D19 -> 1.1510189 | E20: =E18/E19 -> 0.56106153 | F20: =F18/F19 -> 1.1083574 | G20: =G18/G19 -> 1.1823565 | H20: =H18/H19 -> 0.97403913 | I20: =I18/I19 -> 1.0086432
B22: Sales growth Index
B23: Sales growth (current year) | C23: =Historical!F8 -> -0.13486792 | D23: =Historical!G8 -> 0.088822519 | E23: =Historical!H8 -> 0.83332707 | F23: =Historical!I8 -> 0.13383116 | G23: =Historical!J8 -> 0.05450711 | H23: =Historical!K8 -> -0.035324503 | I23: =Historical!L8 -> 0.098599725
B24: Sales growth (previous year) | C24: =Historical!E8 -> 0.17827701 | D24: =Historical!F8 -> -0.13486792 | E24: =Historical!G8 -> 0.088822519 | F24: =Historical!H8 -> 0.83332707 | G24: =Historical!I8 -> 0.13383116 | H24: =Historical!J8 -> 0.05450711 | I24: =Historical!K8 -> -0.035324503
B25: Sales growth Index | C25: =C23/C24 -> -0.75650763 | D25: =D23/D24 -> -0.65858894 | E25: =E23/E24 -> 9.3819347 | F25: =F23/F24 -> 0.16059859 | G25: =G23/G24 -> 0.40728267 | H25: =H23/H24 -> -0.64807147 | I25: =I23/I24 -> -2.7912558
B27: Depreciation index
B28: Depreciation ratio ( pervious year) | C28: =Historical!E25/(Historical!E25+Historical!E58) -> 0.060598335 | D28: =Historical!F25/(Historical!F25+Historical!F58) -> 0.064012302 | E28: =Historical!G25/(Historical!G25+Historical!G58) -> 0.067230875 | F28: =Historical!H25/(Historical!H25+Historical!H58) -> 0.056676835 | G28: =Historical!I25/(Historical!I25+Historical!I58) -> 0.066776263 | H28: =Historical!J25/(Historical!J25+Historical!J58) -> 0.067742657 | I28: =Historical!K25/(Historical!K25+Historical!K58) -> 0.069586993
B29: Depreciation Ratio ( Currrent year) | C29: =Historical!F25/(Historical!F25+Historical!F58) -> 0.064012302 | D29: =Historical!G25/(Historical!G25+Historical!G58) -> 0.067230875 | E29: =Historical!H25/(Historical!H25+Historical!H58) -> 0.056676835 | F29: =Historical!I25/(Historical!I25+Historical!I58) -> 0.066776263 | G29: =Historical!J25/(Historical!J25+Historical!J58) -> 0.067742657 | H29: =Historical!K25/(Historical!K25+Historical!K58) -> 0.069586993 | I29: =Historical!L25/(Historical!L25+Historical!L58) -> 0.07550746
B30: Depreciation index | C30: =C28/C29 -> 0.94666703 | D30: =D28/D29 -> 0.95212656 | E30: =E28/E29 -> 1.1862143 | F30: =F28/F29 -> 0.84875722 | G30: =G28/G29 -> 0.98573433 | H30: =H28/H29 -> 0.97349597 | I30: =I28/I29 -> 0.92159097
B32: SG&A Expense Index
B33: SG&A Margin (current year) | C33: =Historical!F17 -> 0.046763767 | D33: =Historical!G17 -> 0.030248375 | E33: =Historical!H17 -> 0.023768369 | F33: =Historical!I17 -> 0.039557725 | G33: =Historical!J17 -> 0.032844588 | H33: =Historical!K17 -> 0.03667725 | I33: =Historical!L17 -> 0.20540249
B34: SG&A Margin (previous year) | C34: =Historical!E17 -> 0.03446323 | D34: =Historical!F17 -> 0.046763767 | E34: =Historical!G17 -> 0.030248375 | F34: =Historical!H17 -> 0.023768369 | G34: =Historical!I17 -> 0.039557725 | H34: =Historical!J17 -> 0.032844588 | I34: =Historical!K17 -> 0.03667725
B35: SG&A Expense Index | C35: =C33/C34 -> 1.3569177 | D35: =D33/D34 -> 0.64683358 | E35: =E33/E34 -> 0.78577344 | F35: =F33/F34 -> 1.6643012 | G35: =G33/G34 -> 0.83029518 | H35: =H33/H34 -> 1.1166908 | I35: =I33/I34 -> 5.6002697
B37: Accruals Ratio
B38: EBIT | C38: =Historical!F19-Historical!F25 -> 7567 | D38: =Historical!G19-Historical!G25 -> 15499 | E38: =Historical!H19-Historical!H25 -> 33113 | F38: =Historical!I19-Historical!I25 -> 10996 | G38: =Historical!J19-Historical!J25 -> 19985 | H38: =Historical!K19-Historical!K25 -> 13416 | I38: =Historical!L19-Historical!L25 -> 19745
B39: CFO | C39: =Historical!F75 -> 12785 | D39: =Historical!G75 -> 18831 | E39: =Historical!H75 -> 26270 | F39: =Historical!I75 -> 23323 | G39: =Historical!J75 -> 12078 | H39: =Historical!K75 -> 20899 | I39: =Historical!L75 -> 25152
B40: Total Assets | C40: =Historical!F69 -> 131820 | D40: =Historical!G69 -> 147163 | E40: =Historical!H69 -> 196485 | F40: =Historical!I69 -> 210539 | G40: =Historical!J69 -> 227898 | H40: =Historical!K69 -> 240445 | I40: =Historical!L69 -> 269676
B41: Accruals Ratio | C41: =(C38-C39)/C40 -> -0.039584282 | D41: =(D38-D39)/D40 -> -0.022641561 | E41: =(E38-E39)/E40 -> 0.034827086 | F41: =(F38-F39)/F40 -> -0.058549722 | G41: =(G38-G39)/G40 -> 0.034695346 | H41: =(H38-H39)/H40 -> -0.031121462 | I41: =(I38-I39)/I40 -> -0.020049986
B43: Leverage Index
B44: Leverage ratio ( current year) | C44: =SUM('Data Sheet'!E59:E60)/'Data Sheet'!E66 -> 0.72235624 | D44: =SUM('Data Sheet'!F59:F60)/'Data Sheet'!F66 -> 0.69007155 | E44: =SUM('Data Sheet'!G59:G60)/'Data Sheet'!G66 -> 0.65749548 | F44: =SUM('Data Sheet'!H59:H60)/'Data Sheet'!H66 -> 0.68796755 | G44: =SUM('Data Sheet'!I59:I60)/'Data Sheet'!I66 -> 0.65919403 | H44: =SUM('Data Sheet'!J59:J60)/'Data Sheet'!J66 -> 0.66937969 | I44: =SUM('Data Sheet'!K59:K60)/'Data Sheet'!K66 -> 0.62898812
B45: Leverage ratio ( previous year) | C45: =SUM('Data Sheet'!D59:D60)/'Data Sheet'!D66 -> 0.69689974 | D45: =SUM('Data Sheet'!E59:E60)/'Data Sheet'!E66 -> 0.72235624 | E45: =SUM('Data Sheet'!F59:F60)/'Data Sheet'!F66 -> 0.69007155 | F45: =SUM('Data Sheet'!G59:G60)/'Data Sheet'!G66 -> 0.65749548 | G45: =SUM('Data Sheet'!H59:H60)/'Data Sheet'!H66 -> 0.68796755 | H45: =SUM('Data Sheet'!I59:I60)/'Data Sheet'!I66 -> 0.65919403 | I45: =SUM('Data Sheet'!J59:J60)/'Data Sheet'!J66 -> 0.66937969
B46: Leverage Index | C46: =C44/C45 -> 1.0365282 | D46: =D44/D45 -> 0.95530642 | E46: =E44/E45 -> 0.9527932 | F46: =F44/F45 -> 1.0463457 | G46: =G44/G45 -> 0.95817604 | H46: =H44/H45 -> 1.0154517 | I46: =I44/I45 -> 0.9396582
B48: Benish M Score
B50: Particulars | C50: =C5 -> 43921 | D50: =D5 -> 44286 | E50: =E5 -> 44651 | F50: =F5 -> 45016 | G50: =G5 -> 45382 | H50: =H5 -> 45747 | I50: =I5 -> 46112
B51: Final Score | C51: =-4.84+0.92*(C10)+0.528*(C15)+0.404*(C20)+0.892*(C25)+0.115*(C30)-0.172*(C35)+4.679*(C41)-0.372*(C46) -> -4.3139566 | D51: =-4.84+0.92*(D10)+0.528*(D15)+0.404*(D20)+0.892*(D25)+0.115*(D30)-0.172*(D35)+4.679*(D41)-0.372*(D46) -> -4.1962927 | E51: =-4.84+0.92*(E10)+0.528*(E15)+0.404*(E20)+0.892*(E25)+0.115*(E30)-0.172*(E35)+4.679*(E41)-0.372*(E46) -> 4.9127631 | F51: =-4.84+0.92*(F10)+0.528*(F15)+0.404*(F20)+0.892*(F25)+0.115*(F30)-0.172*(F35)+4.679*(F41)-0.372*(F46) -> -3.3060271 | G51: =-4.84+0.92*(G10)+0.528*(G15)+0.404*(G20)+0.892*(G25)+0.115*(G30)-0.172*(G35)+4.679*(G41)-0.372*(G46) -> -2.8883911 | H51: =-4.84+0.92*(H10)+0.528*(H15)+0.404*(H20)+0.892*(H25)+0.115*(H30)-0.172*(H35)+4.679*(H41)-0.372*(H46) -> -3.9676101 | I51: =-4.84+0.92*(I10)+0.528*(I15)+0.404*(I20)+0.892*(I25)+0.115*(I30)-0.172*(I35)+4.679*(I41)-0.372*(I46) -> -6.8536733
B53: Probability Of Earning Mnaipulation | C53: =IF(C51>-1.78," Earning Manipulation","No Earning Manipulation") -> No Earning Manipulation | D53: =IF(D51>-1.78," Earning Manipulation","No Earning Manipulation") -> No Earning Manipulation | E53: =IF(E51>-1.78," Earning Manipulation","No Earning Manipulation") -> Earning Manipulation | F53: =IF(F51>-1.78," Earning Manipulation","No Earning Manipulation") -> No Earning Manipulation | G53: =IF(G51>-1.78," Earning Manipulation","No Earning Manipulation") -> No Earning Manipulation | H53: =IF(H51>-1.78," Earning Manipulation","No Earning Manipulation") -> No Earning Manipulation | I53: =IF(I51>-1.78," Earning Manipulation","No Earning Manipulation") -> No Earning Manipulation

Sheet Conclusion
B2: Conclusion
A5: # | B5: key risk & considration
B7: Upside Drivers
B8: Stable CFO - cash flow from operation shows a table growth
B9: Steel price - Increase in steel price increase revenue
B10: steel demand - estimate of 7.7% CAGR of automobile industry from 2026-2030 which increase demad of steel
B13: Downside risk
B14: Raw material cost - increase in primary raw metrial (iron ore , thermal coal , etc.) cost
B15: Market Risk - Risk of export due to regulatory changes
B16: Infrastructure Risk - Increasing production capacity from 35.7 MTPA to 50 MTPA increase infrastructure risk
A18: # | B18: Recommendation
B20: Based on our Discounted Cash Flow (DCF) valuation, the stock's intrinsic value is estimated at ₹758 per share, compared with the current market price of ₹1,306 per share.
B21: This implies that the stock is trading at approximately 1.72x its intrinsic value, suggesting a significant overvaluation relative to our DCF-based assessment.
B23: Key Highlights
B24: app. 12.08% of annual CAGR have generated throughout 10 year
B25: negative cash conversion cycle show cash collection from debtor is higher than paying cash to supplier
B26: despite having in capital intensive industry its depreciation as a % of sales is low
B28: Investment recommendation - Hold

Sheet Cash flow data sheet
B1: 42064 | C1: 42430 | D1: 42795 | E1: 43160 | F1: 43525 | G1: 43891 | H1: 44256 | I1: 44621 | J1: 44986 | K1: 45352 | L1: 45717 | M1: 46082
A2: Cash from Operating Activity - | B2: 7876 | C2: 6897 | D2: 7888 | E2: 12379 | F2: 14633 | G2: 12785 | H2: 18831 | I2: 26270 | J2: 23323 | K2: 12078 | L2: 20899 | M2: 25152
A3: Profit from operations | B3: 8850 | C3: 6614 | D3: 11994 | E3: 14920 | F3: 18844 | G3: 12301 | H3: 19455 | I3: 38913 | J3: 20856 | K3: 28472 | L3: 23553 | M3: 32085
A4: Receivables | B4: -207 | C4: -294 | D4: -1352 | E4: -640 | F4: -2203 | G4: 2458 | H4: 72 | I4: -1884 | J4: 317 | K4: -154 | L4: -866 | M4: -3686
A5: Inventory | B5: -2854 | C5: 2578 | D5: -3065 | E5: -1199 | F5: -1741 | G5: 744 | H5: -335 | I5: -15593 | J5: 704 | K5: -3284 | L5: 2609 | M5: -3176
A6: Payables | B6: 2543 | C6: -2143 | D6: 1561 | E6: 2514 | F6: 3406 | G6: 183 | H6: 1348 | I6: 13013 | J6: 4965 | K6: -7235 | L6: -1096 | M6: 5517
A7: Loans Advances | B7: 286 | C7: 0 | D7: 0 | E7: 0 | F7: 0 | G7: 0 | H7: 0 | I7: 0 | J7: 0 | K7: 0 | L7: 0 | M7: 0
A8: Other WC items | B8: 31 | C8: 351 | D8: -1013 | E8: -1776 | F8: -1043 | G8: -1746 | H8: 221 | I8: -2800 | J8: -2881 | K8: -2942 | L8: -1328 | M8: -2363
A9: Working capital changes | B9: -202 | C9: 491 | D9: -3869 | E9: -1101 | F9: -1581 | G9: 1639 | H9: 1306 | I9: -7264 | J9: 3105 | K9: -13615 | L9: -681 | M9: -3708
A10: Direct taxes | B10: -773 | C10: -207 | D10: -237 | E10: -1440 | F10: -2630 | G10: -1155 | H10: -1930 | I10: -5379 | J10: -638 | K10: -2779 | L10: -1973 | M10: -3225
A11: Cash from Investing Activity + | B11: -7372 | C11: -3857 | D11: -5094 | E11: -4529 | F11: -11387 | G11: -19589 | H11: -9410 | I11: -14748 | J11: -10730 | K11: -14467 | L11: -17012 | M11: 18690
A12: Cash from Financing Activity + | B12: -169 | C12: -3151 | D12: -2710 | E12: -8185 | F12: 1753 | G12: 5189 | H12: -1444 | I12: -14657 | J12: -5977 | K12: -5005 | L12: -262 | M12: -16111
A13: Net Cash Flow | B13: 334 | C13: -111 | D13: 84 | E13: -335 | F13: 4999 | G13: -1615 | H13: 7977 | I13: -3135 | J13: 6616 | K13: -7394 | L13: 3625 | M13: 27731
... A15: CFO/OP | B15: 0.92 | C15: 1.11 | D15: 0.66 | E15: 0.93 | F15: 0.91 | G15: 1.18 | H15: 1.03 | I15: 0.81 | J15: 1.3 | K15: 0.53 | L15: 1.01 | M15: 0.97

Sheet Data Sheet
A1: COMPANY NAME | B1: JSW STEEL LTD | E1: =B1 -> JSW STEEL LTD
A2: LATEST VERSION | B2: 2.1 | E2: PLEASE DO NOT MAKE ANY CHANGES TO THIS SHEET
A3: CURRENT VERSION | B3: 2.1
A5: META
A6: Number of shares | B6: =IF(B9>0, B9/B8, 0) -> 244.5454
A7: Face Value | B7: 1
A8: Current Price | B8: 1278
A9: Market Capitalization | B9: 312529.02
A15: PROFIT & LOSS
A16: Report Date | B16: 42825 | C16: 43190 | D16: 43555 | E16: 43921 | F16: 44286 | G16: 44651 | H16: 45016 | I16: 45382 | J16: 45747 | K16: 46112
A17: Sales | B17: 55604 | C17: 71933 | D17: 84757 | E17: 73326 | F17: 79839 | G17: 146371 | H17: 165960 | I17: 175006 | J17: 168824 | K17: 185470
A18: Raw Material Cost | B18: 29749 | C18: 38781 | D18: 43796 | E18: 39000 | F18: 32856 | G18: 62871 | H18: 95970 | I18: 94754 | J18: 89169 | K18: 91872
A19: Change in Inventory | B19: 1486 | C19: -244 | D19: 590 | E19: 270 | F19: 348 | G19: 3601 | H19: 2636 | I19: 3087 | J19: -829 | K19: -4719
A20: Power and Fuel | B20: 4883 | C20: 5697 | D20: 7053 | E20: 6272 | F20: 5985 | G20: 11289 | H20: 17452 | I20: 15127 | J20: 16161 | K20: 16152
A21: Other Mfr. Exp | B21: 6887 | C21: 8713 | D21: 10158 | E21: 10243 | F21: 16247 | G21: 29726 | H21: 26224 | I21: 29716 | J21: 28950
A22: Employee Cost | B22: 1700 | C22: 1843 | D22: 2489 | E22: 2839 | F22: 2506 | G22: 3493 | H22: 3915 | I22: 4591 | J22: 4798 | K22: 5285
A23: Selling and admin | B23: 323 | C23: 277 | D23: 602 | E23: 450 | F23: 404 | G23: 557 | H23: 1018 | I23: 894 | J23: 912
A24: Other Expenses | B24: 1240 | C24: 1462 | D24: 2319 | E24: 2979 | F24: 2011 | G24: 2922 | H24: 5547 | I24: 4854 | J24: 5280 | K24: 38096
A25: Other Income | B25: 18 | C25: -177 | D25: 196 | E25: -289 | F25: 473 | G25: 1600 | H25: 1561 | I25: 1500 | J25: 73 | K25: 18607
A26: Depreciation | B26: 3430 | C26: 3387 | D26: 4041 | E26: 4246 | F26: 4679 | G26: 6001 | H26: 7474 | I26: 8172 | J26: 9309 | K26: 9601
A27: Interest | B27: 3768 | C27: 3701 | D27: 3917 | E27: 4265 | F27: 3957 | G27: 4968 | H27: 6902 | I27: 8105 | J27: 8412 | K27: 9102
A28: Profit before tax | B28: 5128 | C28: 7651 | D28: 11168 | E28: 3013 | F28: 12015 | G28: 29745 | H28: 5655 | I28: 13380 | J28: 5077 | K28: 29250
A29: Tax | B29: 1674 | C29: 1538 | D29: 3644 | E29: -906 | F29: 4142 | G29: 8807 | H29: 1516 | I29: 4407 | J29: 1586 | K29: 3742
A30: Net profit | B30: 3523 | C30: 6214 | D30: 7639 | E30: 4030 | F30: 7911 | G30: 20665 | H30: 4144 | I30: 8812 | J30: 3504 | K30: 22316
A31: Dividend Amount | B31: 677.25 | C31: 966.4 | D31: 1234.1 | E31: 602 | F31: 1963 | G31: 5222.35 | H31: 1023.4 | I31: 2226.5 | J31: 854 | K31: 2165.5
A40: Quarters
A41: Report Date | B41: 45291 | C41: 45382 | D41: 45473 | E41: 45565 | F41: 45657 | G41: 45747 | H41: 45838 | I41: 45930 | J41: 46022 | K41: 46112
A42: Sales | B42: 41940 | C42: 46269 | D42: 42943 | E42: 39684 | F42: 41378 | G42: 44819 | H42: 43147 | I42: 45152 | J42: 45991 | K42: 51180
A43: Expenses | B43: 34776 | C43: 40243 | D43: 37445 | E43: 34309 | F43: 35799 | G43: 38684 | H43: 35671 | I43: 38125 | J43: 39612 | K43: 42716
A44: Other Income | B44: 194 | C44: 242 | D44: 164 | E44: -189 | F44: 50 | G44: 186 | H44: 350 | I44: 284 | J44: -256 | K44: 18229
A45: Depreciation | B45: 2059 | C45: 2194 | D45: 2209 | E45: 2267 | F45: 2336 | G45: 2497 | H45: 2537 | I45: 2554 | J45: 2362 | K45: 2148
A46: Interest | B46: 1996 | C46: 2062 | D46: 2073 | E46: 2130 | F46: 2115 | G46: 2094 | H46: 2217 | I46: 2413 | J46: 2304 | K46: 2168
A47: Profit before tax | B47: 3303 | C47: 2012 | D47: 1380 | E47: 789 | F47: 1178 | G47: 1730 | H47: 3072 | I47: 2344 | J47: 1457 | K47: 22377
A48: Tax | B48: 853 | C48: 690 | D48: 513 | E48: 385 | F48: 459 | G48: 229 | H48: 863 | I48: 698 | J48: -953 | K48: 3134
A49: Net profit | B49: 2415 | C49: 1299 | D49: 845 | E49: 439 | F49: 717 | G49: 1503 | H49: 2184 | I49: 1623 | J49: 2139 | K49: 16370
A50: Operating Profit | B50: 7164 | C50: 6026 | D50: 5498 | E50: 5375 | F50: 5579 | G50: 6135 | H50: 7476 | I50: 7027 | J50: 6379 | K50: 8464
A55: BALANCE SHEET
A56: Report Date | B56: 42825 | C56: 43190 | D56: 43555 | E56: 43921 | F56: 44286 | G56: 44651 | H56: 45016 | I56: 45382 | J56: 45747 | K56: 46112
A57: Equity Share Capital | B57: 301 | C57: 302 | D57: 301 | E57: 301 | F57: 302 | G57: 301 | H57: 301 | I57: 305 | J57: 305 | K57: 305
A58: Reserves | B58: 22346 | C58: 27696 | D58: 34494 | E58: 36298 | F58: 45308 | G58: 66996 | H58: 65394 | I58: 77364 | J58: 79191 | K58: 99748
A59: Borrowings | B59: 43334 | C59: 39393 | D59: 47396 | E59: 61423 | F59: 66727 | G59: 72237 | H59: 80853 | I59: 87984 | J59: 98752 | K59: 99310
A60: Other Liabilities | B60: 22024 | C60: 24579 | D60: 32606 | E60: 33798 | F60: 34826 | G60: 56951 | H60: 63991 | I60: 62245 | J60: 62197 | K60: 70313
A61: Total | B61: 88005 | C61: 91970 | D61: 114797 | E61: 131820 | F61: 147163 | G61: 196485 | H61: 210539 | I61: 227898 | J61: 240445 | K61: 269676
A62: Net Block | B62: 58730 | C62: 57848 | D62: 62644 | E62: 62085 | F62: 64917 | G62: 99880 | H62: 104452 | I62: 112461 | J62: 124466 | K62: 117552
A63: Capital Work in Progress | B63: 4363 | C63: 5950 | D63: 11889 | E63: 27191 | F63: 32566 | G63: 16905 | H63: 22166 | I63: 29676 | J63: 21007 | K63: 21892
A64: Investments | B64: 1366 | C64: 1469 | D64: 1894 | E64: 1259 | F64: 7427 | G64: 4940 | H64: 4806 | I64: 7246 | J64: 15217 | K64: 10218
A65: Other Assets | B65: 23546 | C65: 26703 | D65: 38370 | E65: 41285 | F65: 42253 | G65: 74760 | H65: 79115 | I65: 78515 | J65: 79755 | K65: 120014
A66: Total | B66: 88005 | C66: 91970 | D66: 114797 | E66: 131820 | F66: 147163 | G66: 196485 | H66: 210539 | I66: 227898 | J66: 240445 | K66: 269676
A67: Receivables | B67: 4149 | C67: 4704 | D67: 7160 | E67: 4505 | F67: 4486 | G67: 7457 | H67: 7134 | I67: 7548 | J67: 8415 | K67: 11260
... A69: Cash & Bank | B69: 1485 | C69: 1063 | D69: 6187 | E69: 12003 | F69: 12813 | G69: 17383 | H69: 20714 | I69: 12348 | J69: 13285 | K69: 40989
A70: No. of Equity Shares | B70: 3012984690 | C70: 3016231580 | D70: 3011711464 | E70: 3011711464 | F70: 3015766346 | G70: 3016603583 | H70: 3020456419 | I70: 3052602319 | J70: 3052602319
A71: New Bonus Shares
A72: Face value | B72: 1 | C72: 1 | D72: 1 | E72: 1 | F72: 1 | G72: 1 | H72: 1 | I72: 1 | J72: 1 | K72: 1
A80: CASH FLOW:
A81: Report Date | B81: 42825 | C81: 43190 | D81: 43555 | E81: 43921 | F81: 44286 | G81: 44651 | H81: 45016 | I81: 45382 | J81: 45747 | K81: 46112
A82: Cash from Operating Activity | B82: 7888 | C82: 12379 | D82: 14633 | E82: 12785 | F82: 18831 | G82: 26270 | H82: 23323 | I82: 12078 | J82: 20899 | K82: 25152
A83: Cash from Investing Activity | B83: -5094 | C83: -4529 | D83: -11387 | E83: -19589 | F83: -9410 | G83: -14748 | H83: -10730 | I83: -14467 | J83: -17012 | K83: 18690
A84: Cash from Financing Activity | B84: -2710 | C84: -8185 | D84: 1753 | E84: 5189 | F84: -1444 | G84: -14657 | H84: -5977 | I84: -5005 | J84: -262 | K84: -16111
A85: Net Cash Flow | B85: 84 | C85: -335 | D85: 4999 | E85: -1615 | F85: 7977 | G85: -3135 | H85: 6616 | I85: -7394 | J85: 3625 | K85: 27731
A90: PRICE: | B90: 188.2 | C90: 288.15 | D90: 293.05 | E90: 146.25 | F90: 468.45 | G90: 732.65 | H90: 688.1 | I90: 830.2 | J90: 1063.2 | K90: 1122.5
A92: DERIVED:
A93: Adjusted Equity Shares in Cr | B93: 241.72 | C93: 241.72 | D93: 241.72 | E93: 241.72 | F93: 241.72 | G93: 241.72 | H93: 241.72 | I93: 244.55 | J93: 244.55 | K93: 244.55
